{"A2HOI48JK8838M": 0, "A1YIPEY7HX73S7": 1, "A2QCGHIJ2TCLVP": 2, "A2R4UNHFJBA6PY": 3, "A1606LA683WZZU": 4, "A1YY53NQXFKMRN": 5, "A3R0NQ9E53JHYQ": 6, "A35YXEDATMIJ9S": 7, "A3CRJ1Q73RB25F": 8, "A1Y39RECFXEGNL": 9, "A3O0BXK3SZ6FE0": 10, "AWVF9EWW3BXYV": 11, "ACUGBCEADYT6D": 12, "A3S3R88HA0HZG3": 13, "A16VM71BLBCMMK": 14, "A1RRX286ZRI830": 15, "A2CAF6DVZOHMHG": 16, "A1M1Y5UGONAW06": 17, "AHLTB5YPI6JX1": 18, "A3LSOG7F3ZCJ65": 19, "A2NUBL2UYWPBWR": 20, "A2AVMDTFW79N2N": 21, "A2KJIX9GXBCVWH": 22, "A15R5T6T1TBSJX": 23, "A3TX3N3YORDUBY": 24, "A3045PONRA3KZ2": 25, "A326D766H2I6RR": 26, "A1B95QB8NVYOSM": 27, "A1EJ9DSKSM0UN1": 28, "A2N0ORB4ES548E": 29, "AC400LZPY74N1": 30, "AV00VR0BWTQI6": 31, "A32O98PFC3OP7K": 32, "A6QG9LM5WL0AQ": 33, "AOP2ZRNSHY2Z3": 34, "A2JP9E1H0SF392": 35, "A3IOCPLIMYDBCD": 36, "AG0830H1DBLD": 37, "A35Q0RBM3YNQNF": 38, "A39WWMBA0299ZF": 39, "A2JCJJNY43QQIV": 40, "A3UQ3HOJ37Q24Q": 41, "A2MS6GT9F0CB01": 42, "A18L008KVHQ1AM": 43, "AICOFZH7HCKGY": 44, "A1NOKJM3Y13CG9": 45, "A2CRHEUW1ATJ65": 46, "ALT082QMA75B6": 47, "A10K606KWGOA2Y": 48, "A3U16LITWT2PQJ": 49, "AJ9VB45YRX8C9": 50, "A39ECS1S0CJ0X9": 51, "AI2YYV9D3LS8P": 52, "A1O3UXMAN62I6V": 53, "A2BHOZILR7SY9": 54, "A2WCQTORZ1G1NG": 55, "A3VXLOGI23ZHHX": 56, "A1O5T5R8A6EG7U": 57, "A2YG3QYP5BFNYG": 58, "A3IE9F9PFLNUYN": 59, "A3P51JNV7DHB2L": 60, "ACMSQCH1H7JZD": 61, "AIWN1666ZUAP9": 62, "A3OP1NKCMO99U2": 63, "A11LI37SHY97N": 64, "AUPUDYKYU6431": 65, "A21M3YYEERMG3D": 66, "A2NOIGZ6VV86IB": 67, "A3GBARYNM6S4G6": 68, "A2Z06I0Q4FMFHP": 69, "A914TQVHI872U": 70, "A2WRHFD1BJ8W7A": 71, "A2L77YQRAEA1YZ": 72, "ADLZKR4HKJ83S": 73, "A28W77RPDZK7AZ": 74, "A30YSE0M6LM61J": 75, "AO6XYV4ZKJ2UW": 76, "A2QJ710FJC9E40": 77, "A3IGCB651CBUS5": 78, "A6VOQ7HCFLPGP": 79, "A4HUA3IU17AP1": 80, "A1CKAZZ3Z647NA": 81, "A11YA52GQ0D6B6": 82, "A3DZFW2XL5S6XK": 83, "AXBTO9HB020I7": 84, "A37DBZJQ3FFDX": 85, "A2IV70BWQBUF32": 86, "A3BM33D682B9XV": 87, "A3MZRGNGM4H7PI": 88, "A1I8QPILZMTELT": 89, "A28BA1RUNCWUNZ": 90, "A1P9WLE3DFEMQ2": 91, "A1KGCBNUMKYV7L": 92, "A24D70VHLXXH85": 93, "AUFJRMYL1K9OZ": 94, "A23LYYPZPV3W21": 95, "AENH50GW3OKDA": 96, "AEJCGRCBX8KCQ": 97, "A2RMXI5NNXFES7": 98, "AA8A6NJUVPNO": 99, "A29MN2UX5ZN16S": 100, "A3VNJJU5GOS97N": 101, "ASSXBJAWV8766": 102, "A38FB414U3B72L": 103, "A2GO4MLC7NCV1L": 104, "A2JNO9OR8FGNR4": 105, "A1ZKGSDVP057L9": 106, "A3HSC1S1WID15T": 107, "A1ISJC5E0GD68O": 108, "A3HG5MZ9QJMINU": 109, "A21LIZOWUJ152K": 110, "A12GK5JUYAV0HM": 111, "A2ANNQ7WTLZUD7": 112, "A34EQAIKKUWYYW": 113, "AV9TAY68SUZRV": 114, "A3MY4POKX3EQEX": 115, "AIWSX8DYYGBJY": 116, "A2ZLPBWFUQPUJA": 117, "A22YTUDL95N29U": 118, "ANE1HNWMHEB7G": 119, "A20VCG18UDO3TL": 120, "A3PH249MRUMLAH": 121, "A31ZXB9VUW2HQP": 122, "A3SZ1B3N4NQNS9": 123, "A1JXY9I578VQ3O": 124, "AXVH1LLNSSE41": 125, "A239ILDOHMMGUV": 126, "A2BJXOROYN18WY": 127, "A3PPEJY11SIL3Z": 128, "A3N1R7KXEDTW1J": 129, "ASHMBNORPUHAK": 130, "AZ90LWO8QPGV1": 131, "AN62VG516BIOU": 132, "A3AZM2RI2QXWSO": 133, "ASODUN15U3MLP": 134, "A34AKD96BXX0HZ": 135, "A3OICFS78GXXIJ": 136, "A2EG5WO6VCFDQ5": 137, "A14CXGHPONCD41": 138, "AFC92OVO2FT69": 139, "A1BEDKI1OQFD5H": 140, "A1LY4LT62BHY1X": 141, "A24L28AJZKXALL": 142, "A1E7EX9LUM7TOF": 143, "A2ZFE69V0T71HN": 144, "AUAI9MEBEBLL7": 145, "A3F8PR8105I7MA": 146, "A1F29W231WNU90": 147, "A3P0VHR9YAIR6P": 148, "AZ34737QMSG8Q": 149, "A21BOTUYRKB30M": 150, "A30Q7HNAJAMQXU": 151, "A22BKY1TAIN2NR": 152, "AD6M0QYWZ8ACF": 153, "AK6CEEE9QC2UM": 154, "A29Y41NL8RA1BP": 155, "A3C0ZGHGJNYEMM": 156, "AAF5D1LTFGB7L": 157, "ARCNPR5YHHP2X": 158, "AIIZTJHZLV158": 159, "A3M2MBDA0F0U3B": 160, "A1TK2US40LPJNH": 161, "A2GKWUF75ZPWIM": 162, "A26C062ZW07V2Y": 163, "A15DH2ICDH1MJN": 164, "A31EXCSFPH9XG0": 165, "AGV6KOEXODL1U": 166, "A3OGA76E22L5CU": 167, "A17O2BER0O0P1K": 168, "A1MELG1UFSXAMV": 169, "AR7EOI1I0D7Q7": 170, "ARKPBV91DYWZF": 171, "ARBVV2X30JNKA": 172, "A2LUOPJNWOESF1": 173, "A1VVXGL8GI2II4": 174, "A1ZZSLTEMTV4HD": 175, "A38KYGR07SUF21": 176, "A2YCLJNOE7JGCW": 177, "A237XY0O6V3UE": 178, "A3IQGM4GW25ZA8": 179, "A3L714OY25JG33": 180, "A3HAQ03H9C99G7": 181, "A1IN5TM9AD6045": 182, "AD8JK9PUC5H0A": 183, "AEVXRGD91MH5U": 184, "AYB2RR9WW2OVR": 185, "A2GVRTQYWV15IO": 186, "A3B2S40YG11CTQ": 187, "A3TE23IJ6GITLF": 188, "A2Q9KC6JXDG5JA": 189, "ANXT431V3MW4Z": 190, "A2N10B0NEZKIOV": 191, "A3JO18FDVDP5U2": 192, "APE5GBFTJSHR9": 193, "A18GJ9MYYO6GCQ": 194, "A13X7XBBT1DN8U": 195, "A1SFKLLC60TL69": 196, "A27JG4ZAJZPCJX": 197, "A66U6BOLQK0H9": 198, "A2PF64RBR1G1SZ": 199, "A3IWRIHT6W3HBP": 200, "A2HW6NZ9TB2ROS": 201, "A2LGYL8CHB7TDG": 202, "A2YIGODNVUPCZG": 203, "A326ORFY46O7CX": 204, "A3VJHHCDBMZF5W": 205, "A3G7JGYNVP1O4L": 206, "A1TPW86OHXTXFC": 207, "A152TZLTJNQNBA": 208, "A2VQCEUCKD36L1": 209, "A1MFMWKPTDFZE8": 210, "A3LDZPJ6OZYIQA": 211, "A2V2I83BSJPCFS": 212, "A2UH1H308KYVMX": 213, "A1G6HZ3CGYEYNN": 214, "A2RSB35G43HTZ6": 215, "A1WIE2SG6ZM6OO": 216, "A1DCBQD9QX2I3J": 217, "A3SCU8S8MC6S4Q": 218, "A3ECGCYX7OGQSV": 219, "A392CQOTI9JR27": 220, "ASTE2P3Z3CE2P": 221, "A1HQ56HXZQJ1WU": 222, "A56VIAK488876": 223, "A2LAFL37V088EU": 224, "A2Q3BW3177V542": 225, "A21O6J200QQQ1D": 226, "A1JI6A2AAJK5V3": 227, "A1KSC91G9AIY2Z": 228, "A1WKQ94M45D8MG": 229, "AFICF7DKHTQ87": 230, "ACYR6O588USK": 231, "A2FSMTNXL81WJ0": 232, "A19WEEGB05YAZ3": 233, "A24RCBRDXRXR0Y": 234, "A2OGXO7G3GUBA8": 235, "A305XM71TF83CY": 236, "A30R8VFR16RE32": 237, "ARXU3FESTWMJJ": 238, "A29E6HV2DT7RCI": 239, "AWPN47SSWK1JV": 240, "A3G007LQX6KGOD": 241, "ATKL8C5IQ56E9": 242, "A8WAYVOKYBLO6": 243, "A2HZ3Z494VS1KG": 244, "A1LKOIZXPQ9VG0": 245, "A3CSWP37MF334K": 246, "A5U5T6EWH90O0": 247, "AHN86VFJIJ2JP": 248, "A2L0NZR1CSYSBP": 249, "AWIF8AR75LL9L": 250, "A2B8GXSCB1R05T": 251, "A1U8VI6I2MFEU8": 252, "A1VS1LL905P5L5": 253, "A5P60H1YBPXBE": 254, "A3R33KMESG0XGQ": 255, "A231LBC8EGPO5L": 256, "A58F10T4OE58C": 257, "AK3402G7FO7AY": 258, "A368H9GFY1JCYC": 259, "AFDJGY68CQL2X": 260, "A2OGN68EIOK1DC": 261, "A34TNH973Q9XT0": 262, "AFEYHFH2GH0QZ": 263, "A2UM324B00HBC8": 264, "AJ68F5QP3GK5S": 265, "A3PWPNZVMNX3PA": 266, "A96JD9312DHWC": 267, "A2LW5AL0KQ9P1M": 268, "A2RQ0AT4XZUIXL": 269, "A18OLZIT0DGVJR": 270, "A93YMZM7YKG1G": 271, "A1Q1T811N4IY3Z": 272, "A1MDDJ2XUPZZOE": 273, "ABIVILOWVFQ9F": 274, "A2V92F5R7MLCVI": 275, "ALDV8DDZWWPYE": 276, "A33SX0AD5PYD9B": 277, "A11OTLEDSW8ZXD": 278, "A2GA64WZK8PKBC": 279, "A1GASYTBITRWV1": 280, "A3TMBYDFP1B9DM": 281, "A1UH8RMD57P34Y": 282, "A2YKWYC3WQJX5J": 283, "A224KM22RQ5CD4": 284, "A25KKXUQQ0OLWB": 285, "A3T6HX48F66512": 286, "A1BTNPMESS99PL": 287, "A2DQVM07J28BKM": 288, "A2FN8FBQAKOZ3B": 289, "A2CZ98V784SRJ0": 290, "A23WE733QT4WGJ": 291, "APD7XINUVG5AL": 292, "A1UUI7PFQ5FU4E": 293, "A3OC93X866Z8TB": 294, "AVU1ILDDYW301": 295, "A2M14CFAMF8J7I": 296, "A2OR94VN7XQCUO": 297, "A2G865VVNGP6E": 298, "A3VGAP2KLCBNBB": 299, "A32JPW72EQDG1X": 300, "A2RYWPOL4NN2KG": 301, "A3FS3FJPD3RJTD": 302, "A226VGZWOEBPGL": 303, "A19XMHRB3G4DIR": 304, "A3MKON3VM0W1TH": 305, "A28I98PKHZZKVB": 306, "A7UPJYPAH73NC": 307, "A27D0VRNOOUNRR": 308, "A19RDMX22VXXSD": 309, "A3V55DVYU80LDS": 310, "AEMSGB00FL3YO": 311, "A35HOUWHAYZZN6": 312, "AQCYEZYS51OBC": 313, "ACVDL5QRCOPE1": 314, "A2F35SS0RKWSO2": 315, "A141R97FHSSUQ0": 316, "AYNTULRNAIPNY": 317, "A1DG75OT3Y49EM": 318, "AHUT55E980RDR": 319, "A2J557IQKW3GCP": 320, "A1EMN4T3ROJDOO": 321, "A1IOSNSY31L5EI": 322, "A7RFDGVXDYQLJ": 323, "A3AKX0DHWTGRGL": 324, "A1WF3V89I4E8BR": 325, "A2VH0UT5EQFB6P": 326, "A2YCUCEYXT9VHX": 327, "A1JEAPSES2HNVE": 328, "A19UTUEBWKIZFT": 329, "A26EQ8U96JA92T": 330, "A3JLERGZ90RMZH": 331, "A3091RP0SPZLMN": 332, "A3DZFEICHK5LF2": 333, "A2SZLNSI5KOQJT": 334, "A2XM8DATMUZHE6": 335, "A3NDUBKYPI47N2": 336, "A1NKOYPJT8ZU8H": 337, "A2B7DW8XZMRMN0": 338, "ACJ9N7ED37HXS": 339, "A25QBCHO0KFT0P": 340, "A2ZY49IDE6TY5I": 341, "A3T4OHEAHOJ700": 342, "A265IEMG2K5R4W": 343, "A3EJ8XHVDC0CWH": 344, "A2WW57XX2UVLM6": 345, "AGEKVD8JPZQMT": 346, "A2W4014S06NAIT": 347, "A2XSSQH4VO5B1L": 348, "A2G04D4QZAXL15": 349, "A3R9X003XW0LNR": 350, "A2S26YGSVXBCFL": 351, "ABL3PCYAQ1Y4C": 352, "A240YCM012LJSO": 353, "A3CW8OUDH7M079": 354, "A37RIRXE3WECZ": 355, "A2V5R832QCSOMX": 356, "A2F540P3L6P5CL": 357, "AOEUN9718KVRD": 358, "A2O421DTA8J0RW": 359, "A108XP24UESKSV": 360, "A39H1GO9E3YQIB": 361, "A1VXIY1511XQK2": 362, "A1IZJVLNMFACS6": 363, "AS44QEHT3KSPK": 364, "A2VHQDJBZH0Y7P": 365, "A28QX31TCIRZF6": 366, "A2MUGFV2TDQ47K": 367, "A3VP3TSPGYRR65": 368, "ATJ22NADXNLD9": 369, "A32NEDX6UVV8DE": 370, "AK9XE112RZO6Q": 371, "AMB2Z4FMDBWQY": 372, "A3JV4PJZD5O4NJ": 373, "A2OXRXUVPXRC9H": 374, "A1EXGL6L0QQ0M5": 375, "A3D9NUCR4RXDPY": 376, "A3FBMSWBJ202SF": 377, "A13MKSASQ6YWL7": 378, "A1CEG62GJ3BI5U": 379, "A2CJLDPPANU020": 380, "AJ9AE2BVND0GS": 381, "A2OW1FKQFPIA5D": 382, "A1H6SBO7R007I8": 383, "A24O15MYDNLZBE": 384, "A22CW0ZHY3NJH8": 385, "A2RME4353Y911C": 386, "A29VG90T649CSU": 387, "A2YB7DLC3FOR7W": 388, "A2KMV056844YV2": 389, "A1278GKNIB8UZ": 390, "A353U0L2HAMSHV": 391, "ATECU14VUIOJ0": 392, "A3MZNRSDQ32UUH": 393, "A12E0Y0J6584RT": 394, "AKMEY1BSHSDG7": 395, "AX5ZDQUSZG8MI": 396, "A100WO06OQR8BQ": 397, "A1W4F91DH3XPB2": 398, "AR2CNXO5LU4JP": 399, "A3KWR8J6CUUU63": 400, "A1UC3OP4QI0RRU": 401, "AQYEEGNRXM0P1": 402, "A3FOSLM5G1BO63": 403, "A1F7YU6O5RU432": 404, "A199FRO0YFMGED": 405, "AO2AQRPPSTABB": 406, "AMBFK6N4JS5Z2": 407, "A1A2ATQ44P2A7Y": 408, "A2065HBMYDXJ1S": 409, "A3IR834T7AROBT": 410, "A1IHTJWYBLU17P": 411, "A2QWEEYO8QLIMI": 412, "A3P738KVXL2YYM": 413, "A36WTXJBYS3DB6": 414, "AT0E6UBVJMJ6W": 415, "A2ZXBFBA7EKYNR": 416, "A2AOZQ3WTNVVOK": 417, "A1501C38OCSEMA": 418, "A2ZGXQ566SR4FM": 419, "A1SM0G50FP7XKJ": 420, "A1R1BFJCMWX0Y3": 421, "A38Z8ZXX1BPFRL": 422, "A3NHUQ33CFH3VM": 423, "A3C2JQC6R2K52C": 424, "A3QYDL5CDNYN66": 425, "A1SLHI58I09T1K": 426, "A1QS1B2IW9SWHC": 427, "A2OCDK0BOW6UCY": 428, "A2XH6KI5ZLRLPS": 429, "AQY5XBYSENNZQ": 430, "A1ENR0YLS6SM6L": 431, "A299RHMH1M9PIW": 432, "A3JH18T58CY65P": 433, "AZD8SMNGQI98O": 434, "AT28RL25Q2OLK": 435, "A2K4HN6EECBNR3": 436, "A2AGQEL3O3S9H6": 437, "A2C27IQUH9N1Z": 438, "A32XGYDA14KT13": 439, "A3LLJTKU4USS6O": 440, "A2Y8IDC1FKGNJC": 441, "A2KXWUEUE51LGL": 442, "A1HHT7QL47MSE5": 443, "A1HHWNXDC9A87C": 444, "A2RVAGXRH10BP": 445, "AWR4UFLX6W6ZW": 446, "A3LWVPC3KVQAFR": 447, "A15DEX5N1ZG95W": 448, "A3IL4YCLWGPRWJ": 449, "A2GPJR489OIH42": 450, "AU4WXVECP0MDO": 451, "A1HIW8QEDZ26KA": 452, "A3RNP5X8ZGZIEI": 453, "APVEFBIJPTYWU": 454, "A217GQ496NNO1C": 455, "A1XEVVV9HTUH05": 456, "A12UB42W3M4FTS": 457, "AL8SSEC9U7PT1": 458, "A29Q8R8DW9V6H3": 459, "A2WVAAIR2KL7Z0": 460, "A1N11N2Z5BK281": 461, "AGM46BB20Y986": 462, "A1YMXGQQT7YWMN": 463, "A1ECTJJ0QNQPCC": 464, "AH89NYA0C1MB9": 465, "A13EHOQ40ARXDI": 466, "AWP3OETSAYH0V": 467, "AC2BHILNGQJ2Q": 468, "ACVS8I9T74237": 469, "A33EGAQ0DU1QRV": 470, "AGMNSU1CR39RR": 471, "A1IW63HLRVK62L": 472, "A1XZPFZA4CMT82": 473, "A0488385844WNV2OWO9X": 474, "A3SOOHKEHHR6C4": 475, "ASGIVOW34XNQS": 476, "A2I6J570F1KTAU": 477, "A3RNKF0QK2M1R8": 478, "A13BQX5F2A0CQF": 479, "ABZFAANO49IDI": 480, "A3U8ENPSBFO4YG": 481, "A1W88UIK9S4PHM": 482, "AN5XPZ1LPVRU1": 483, "A2IRA7YXCVZEWG": 484, "AA17RVKAHEAFS": 485, "ASSG4O8SXUP2C": 486, "A1M87SBGZN0E0B": 487, "A25QK5VBRFEQIN": 488, "AW1YYDMOAII0I": 489, "A1D336P5ENFFJN": 490, "A3TRM9VHMCKWH6": 491, "A3LJP6NDCTKK6Z": 492, "A3063F7PEA30IM": 493, "A1ILFU8IRJAC1K": 494, "A1C97QPVKH03L8": 495, "A3741P0VRPAYDP": 496, "A2X2Q06U2YO9ZX": 497, "A2M4SJYK2899CW": 498, "A11A05XL3VUOUQ": 499, "A2F04CXDQV30VR": 500, "A2WL17COZQXNYL": 501, "AI6DRIHCFTLVE": 502, "A225OKW47SODNA": 503, "AT2YNTTJ02OTO": 504, "AFE6XVOW8SMV2": 505, "A1PIOXOZ1AZ14U": 506, "A1AIONUPTTDFK4": 507, "AS935YJ1LIR5K": 508, "A1MJ12V42699C3": 509, "A2LQ487PCEOUVE": 510, "A1B5AQUJN16AHX": 511, "AM6OTAYVBL7NM": 512, "A3HDG415KO5AFQ": 513, "A19TEEHU4WNZ40": 514, "A1G2JKKEKAR7YN": 515, "A34Q5DMA3K8GGK": 516, "A1UQBMQLN9KIDE": 517, "AS4P0QUGABH3C": 518, "A23K3O8L45GCQE": 519, "A5VHIX97H8FPU": 520, "A3SGSNBSMJUUGR": 521, "A1X1KB1LVPMTHO": 522, "A3LDLG08Q8D7KF": 523, "A133L22TAC5TA9": 524, "A38JIIHRVTSNYV": 525, "A2FQZKL2KIZACO": 526, "A1F6T228BA5Y7": 527, "A3QS776PDEZ773": 528, "A2TPFWN9C6LY4W": 529, "A3GPAGEFFDWWXN": 530, "A3C9DK18RMNE3B": 531, "A33J53S6YK1UA5": 532, "A1520O7UE0HDWI": 533, "A1UQV5VR85GSY4": 534, "A1QO88MU0PYJON": 535, "A1TP2RW7KDI5AZ": 536, "A110RS7QL8Q1UX": 537, "AZA595ZPIG240": 538, "A19SDJ2TSSL8HI": 539, "A21BVL7PKG9BX8": 540, "A1DNXL8BIR5R8R": 541, "A2G4LKK57XMBL3": 542, "A1UNJ46NSB352E": 543, "A38KK0SZYEH5UD": 544, "AEC90GPFKLAAW": 545, "A3TIL1PC2ZE97B": 546, "A3U6WAJSUQVJVO": 547, "A3C9Q3KTNNLJJ": 548, "A2KLA2OS6TQ2BR": 549, "APS2L706GM4PH": 550, "A15PUBCS4N4G60": 551, "A2X5I60WA32FRV": 552, "A17ZH0JUGO72PH": 553, "A2N8JBTYX5W4T2": 554, "AFU0JH2Z063DS": 555, "ATA098GPRGT01": 556, "A1DF63BNDTB9GU": 557, "A1ZHN4UGF3T55Z": 558, "A186H8P2CH4ORG": 559, "A2A0D0P69E3MRL": 560, "A3KDSFEH3XP990": 561, "AOX4RX9CAAHL4": 562, "A3SF8D9FJ37SLZ": 563, "A2YSY7CIXY2LH2": 564, "A2JSSFJAGDUS56": 565, "A1TXRQSFTVEWMN": 566, "A1FEI4HDXTA454": 567, "A1DYLJWGF7AKT2": 568, "A1P59OKDQV9W68": 569, "A17GI2HXKPXHSU": 570, "A1QFX6MTNCLI66": 571, "A31JNBG3XML5OT": 572, "A1WGPDULPPPXF7": 573, "A2RN6224B2MXMF": 574, "AQU3AJCX7BXZF": 575, "A3QDH7PLL764ZV": 576, "A1ZK5LC434CIYJ": 577, "AAMGE7QU3W2AO": 578, "A1ZWG3ETGDJIR5": 579, "A2BU0OBCKFDUKE": 580, "A2XM8UDOAEMGW8": 581, "A8QGPY3Q9L51N": 582, "A2WFZWRYWLC20S": 583, "A1CBO8TK6LWS07": 584, "A8PHIF1PTRRW4": 585, "A39WD34ROZKJAW": 586, "AVGIVZHEOA4QJ": 587, "A330H3NSXTHEUV": 588, "A2PQSQF1JLAEYZ": 589, "AUOKN045TLJQ": 590, "A2XKRIJKX4HF8N": 591, "A3PL5EW82A4QKW": 592, "A7WLP2ROPFTUQ": 593, "A29EAHK7SP8PIP": 594, "A3BE480SRW37EK": 595, "A2ODA5DCQ7ED73": 596, "ATMHYELYDBIK5": 597, "A1BH4B2GYUPAVF": 598, "ADS5IVBEI6S": 599, "A3E5V5TSTAY3R9": 600, "A3PP9GXEMC7O9H": 601, "A1WX42M589VAMQ": 602, "A1ZNYZ2SM5D3HE": 603, "A2TBZAC0XYHLIB": 604, "A3EZHMGGWY74HY": 605, "A1XVF5DU3N05OM": 606, "A2X3L31KCXBHCL": 607, "A3J029KBNG5MNP": 608, "A13NJZ1M018A7C": 609, "A3LOGP4VA9DX46": 610, "A2JAEZ0FMAMJVW": 611, "A3H7087YTQO9PO": 612, "A2R1HUYHXV7H18": 613, "A37APF2XOO3B5Z": 614, "A14638TGYH7GD9": 615, "A13KW5I9IHQ039": 616, "A4BNJSZVARL5W": 617, "A8QYRG7TW491B": 618, "A22B13EJTZKCTM": 619, "AVJJ2D4G5I0Z4": 620, "AVQZ0JG8OP8P7": 621, "A2R95Z7PTF5ZRO": 622, "AOTMP0OKJOUWI": 623, "A216NSW58Q3SCJ": 624, "A2E3NAL9ECE7VS": 625, "A33Y8C4818EJL0": 626, "AJX9A4Q19UTJU": 627, "A1IH42TUIZ2XJL": 628, "A1A25TP5D0L22V": 629, "A3CG93783LP0FO": 630, "A1FWFCJU2G7TRA": 631, "A17CBPANJ3G5T9": 632, "A2VBBEPR330C5C": 633, "A3ATKSR23880M1": 634, "A246XB5KJX2204": 635, "A2V6W8QRKFONHX": 636, "A3JTJHOO15A3NU": 637, "A1V9PARPFDQH55": 638, "A17HVSEZB2PDQK": 639, "AFCAZIM440BI4": 640, "A2JJGW91A6LIHU": 641, "A15WSZ11YEOKMU": 642, "A1XIFNB0XAMPOZ": 643, "AZWXG6KBXXC2N": 644, "A2B9G3FN56R86G": 645, "A1LNDUIMGLWMMT": 646, "A35LHXY2XGM424": 647, "A2JMJVNTBL7K7E": 648, "A5SJ51NDTXYMG": 649, "A3CLHWWOVI9HMM": 650, "A2WGVNJJCNIQA0": 651, "A3MLY0K05WU4F6": 652, "A25RVSK1RSVC48": 653, "APGX3X3M19FO6": 654, "A25SZV39AG8LUQ": 655, "A18DHHHRTNZAM0": 656, "A1WYKIIR1YN0CY": 657, "A1XAPRM0OO15SO": 658, "AF7FNUMVJV1VJ": 659, "AOP4S6P38IYGN": 660, "A18CX8MRLUE35E": 661, "A2YMS9UK1A9OF2": 662, "A2XHC2FG0YR0F1": 663, "A3MOYKOCIDF1ZR": 664, "A3L2T9Z5QYJYFM": 665, "A3Q0U1143BFYTU": 666, "A30NNLD0AT6J8T": 667, "A24FOXO7AZ7V87": 668, "A6YEAHCVOHKWM": 669, "A19T4E1JMZFUV0": 670, "A3JC9W47X7WYK8": 671, "A16G8LLLHG0SNI": 672, "A3LX8I35QYWVGI": 673, "A2AGVV84CZKSNT": 674, "A15OVM8JWXHVNF": 675, "APSY52Q4Y7VF8": 676, "A2KIVODZRTGY4U": 677, "A1JTUH8W536LMH": 678, "A281NPSIMI1C2R": 679, "A3Q9HY0LU7MN6E": 680, "A2HHAV29CZ1OIE": 681, "A2FNA5903D9E6Y": 682, "A35CCGJDNXUDY9": 683, "A8INT3NMHRUS4": 684, "A1ACF7OZ5Z45HX": 685, "A5CDMTW6JKV5G": 686, "A3BA243AM692SH": 687, "A2M6J4CGEA29JI": 688, "AY8WT4WMDDUX0": 689, "AZ26CDSJ363AH": 690, "A2MBLVMVDLHK1L": 691, "A3HZ687GB0AH7Y": 692, "AUV3OR951650C": 693, "A1LUK8APLC16WK": 694, "A26FEJTPYJ934F": 695, "A39ANVSTOM4L6H": 696, "A2BH04B9G9LOYA": 697, "A3NM0RAYSL6PA8": 698, "A2Z8B2KA8K07DM": 699, "A19KLUZ1XD3SRN": 700, "AJNAYBFLBMUML": 701, "AH147953RD031": 702, "A3M6TSEV71537G": 703, "A2503LT8PZIHAD": 704, "ALNFHVS3SC4FV": 705, "A10ZBR6O8S8OCY": 706, "A2IMLOJ2Z2QEU2": 707, "A25CGBLRJB6X0S": 708, "A3FWVV13DJELLV": 709, "A157UIVPN0NYNN": 710, "A2MO8QZTNYYB98": 711, "A8GR4PH5NW96V": 712, "A89ZZKNDFQH23": 713, "A2L6BT1PVV9YN0": 714, "AUEW0SKOB1XYF": 715, "A2A7FD92SZ4KUK": 716, "A100ZQDV7L8PVV": 717, "A1NIGUK4M2ST8": 718, "A3094EPI56GKZ6": 719, "A2QNMPNXW1QAQ5": 720, "A3JJUCWQK3RP2V": 721, "A216GVMBM978DE": 722, "A2V65KWNOLRV8U": 723, "A1DFTNJDV9X26R": 724, "A2UGT8JVH48A0Z": 725, "A2LAS014NSRW72": 726, "A3N2E1MIZC581U": 727, "A3LT26VKSXZFQM": 728, "AUN84JK9HUKZ7": 729, "A2C3QA2V3O2EB3": 730, "A14T4JDOMP7U9G": 731, "ATQXIVCSUPDW": 732, "A3CP3TIMMV9ROY": 733, "A1NC5TNAMWOX8S": 734, "A1EKKSMQAOO7U3": 735, "A399YOEMK1UNZV": 736, "A2LXG7OMJ758J": 737, "AVRV5NTGXZPAB": 738, "AYA784T1U98HI": 739, "A14EA9WQPSOKMF": 740, "A3AUOH1G7GRM1H": 741, "A3CL1BKRBR9NG7": 742, "A2NY2OSQEVGV15": 743, "A1DPDDPNK8HKV1": 744, "A1QXE7OX7MSL2H": 745, "A5O8VQWAE4FBU": 746, "A1JOCKX0DBY0D5": 747, "A4H12YFC21JJ7": 748, "A1SQVRFPGWQ3HQ": 749, "AUPTKICDH0TGL": 750, "A2D2JE8JC3VNW2": 751, "A262UKJTDZOBUV": 752, "A3AH1V1W7J98WZ": 753, "A2USX601I4L2BQ": 754, "A15HBO5EBRDGTQ": 755, "A3VJ5XEA6RZIA2": 756, "A2NVZNGSRV7ZU7": 757, "A16UO065RCHCGW": 758, "A1XTUTWLWW4EIA": 759, "A3UD2OVCYF78FG": 760, "A2N3TOK3OZKDCQ": 761, "A3DY7DG40RAOSE": 762, "A1EOTWLWMIRVIV": 763, "AO1LUJ8VJ03OZ": 764, "ABSCTKLX9F9IU": 765, "A2YDJ928L04Q1C": 766, "AYZ5RU7CLUY2A": 767, "A21G4URAAP0EN": 768, "A3BQMWY60QAPRX": 769, "A1TEUU3GL87XVV": 770, "A21VGNU5959O85": 771, "A1XEZIHQIUAOR1": 772, "AVE1SXX3A7B24": 773, "A27FB97X0COTAH": 774, "A3E6PP8643YYDU": 775, "A2KJQX0MK4E8GY": 776, "ATW3ZP91LID5R": 777, "A3DD0H3XLCNJ3M": 778, "A3IKTR4WJV7BLP": 779, "A3GOVP6EDD1XDH": 780, "AVTFO4SHPBMFI": 781, "A231N07R3IQHW3": 782, "ACMV0J0RP5YQD": 783, "A3U7URZ105OU2H": 784, "A1ID5QT86H8J9D": 785, "A34XNPNAD1EVB4": 786, "A2ZH82YNEST6CQ": 787, "ATDJ3H36PBC6": 788, "AGWWIU5K88RKB": 789, "A1FCU7GAV5IHGG": 790, "A3R79D9SZA0QDU": 791, "A3D72R3QC333J0": 792, "A1TQ0E67JUOUSC": 793, "A1SKQULOV77NT2": 794, "A11YC63APLB2K9": 795, "A24JL1MU8KCRZ2": 796, "A1A4HS18EQAGWF": 797, "ASE0G6I3ZC0QB": 798, "A3I85Y7QFOEU9M": 799, "A2PP6U0R0FZUW6": 800, "A2GJX2KCUSR0EI": 801, "A3AL9NFNWTRV39": 802, "A15OAS39003U5R": 803, "A277TO3PKKNYDH": 804, "A3IVTAT62XST8A": 805, "A3R9H6OKZHHRJD": 806, "A13WEKTB63G78Y": 807, "AX9C10JD538D9": 808, "A3EOVXI1VZIHUQ": 809, "A3VJ27010XUWTF": 810, "APP35M28G2U51": 811, "A13GZCHAMKWYBT": 812, "A1BI8PUEHA5CHW": 813, "A2QQJY5LT67R2": 814, "A2VJJ2POCLMED7": 815, "ATN4J5VS8Q0YM": 816, "A39650P2CZUUC9": 817, "A2K8CHFQL5U2BP": 818, "A3VS2RYRGDW4HS": 819, "A3I2NABLA9HTUP": 820, "A1Q7A78VSQ5GQ4": 821, "A22S7D0LP8GRDH": 822, "AM18CU72YEWH5": 823, "A24U6WGBZ4P74W": 824, "A1382NUB0AKHTK": 825, "A2YQ7M9GFU3Z65": 826, "A22RIIYSPA3EDH": 827, "A1IDWUYX4QXTUE": 828, "ADFLBRY00Y70G": 829, "APPCJX62WKIIP": 830, "AUH792DXLWGXW": 831, "A1RX2N300NHQAF": 832, "ABQWMANK4AR63": 833, "A37FFWZUGO8L7W": 834, "A3HCZTTUH3CW9Z": 835, "A1M92239OM8KPO": 836, "A3P8ZDHC7XSKSE": 837, "ANHL7BB84WJMF": 838, "A2T9EHCUD7CNEB": 839, "A26BU3ZU0R5IPF": 840, "A20JY8RL920U8H": 841, "A1E3TWWRB1Q7CS": 842, "A1S7YQQGJPPFLG": 843, "AGJN8GZ637X6P": 844, "A2PD27UKAD3Q00": 845, "A1A2F1ZOWOPNJB": 846, "AGA7LFNS3YUXC": 847, "ALDYWG0CPSYUF": 848, "A3SLC8F6VIWXIR": 849, "A16AXQ11SZA8SQ": 850, "A1NEIH01B5X6QL": 851, "A1ZH5ULI4SBO48": 852, "A2OQYSTYR8SSVQ": 853, "A2ZJPDH0YP90SD": 854, "A8FKBLA05XOF0": 855, "A3AO77W3NW2N9G": 856, "A23RQRX7LO7NG8": 857, "A1TPWGBNIYJ76F": 858, "A19XC6Z95GK5AB": 859, "AG7EF0SVBQOUX": 860, "A25NT9MZV9RTR7": 861, "ARARUVZ8RUF5T": 862, "A231YLXS6IQ441": 863, "A3R9AE276DZL5M": 864, "A1V16DTJLH8Z1J": 865, "A34ITQDFC2H0EB": 866, "AALYS669KXNTE": 867, "A19WVSH9MZZG": 868, "AVA18T6I2QYYU": 869, "A1ZEAKUA45EEBK": 870, "A3E396M1AH5ZF9": 871, "A2TI1OLFNCM0D5": 872, "A3ADJ7HRZG8D9B": 873, "A1739RDYJNA6HT": 874, "A3HXDBIN7D54YC": 875, "A3RA9IGBRPLXQ9": 876, "A1MJVKYQHH5RKX": 877, "AEATMJCLSBT9G": 878, "AAFUVVP5DJCWC": 879, "ABZALFYN8WUVT": 880, "A2QBYNH780O937": 881, "A313QFASCV2LA3": 882, "A24MOMTTDNCXYZ": 883, "A3PM8J91NSSL0B": 884, "A1I7VFNY32E552": 885, "A3OZ7ET1JHDX5": 886, "A3I4ZRJ1E5QBUE": 887, "A1I5VBBLEKD6I0": 888, "A2VAWEULL019JO": 889, "ARAX8RK1KC4SW": 890, "A2H3B82GQHA179": 891, "AHQVBCXO2WM5C": 892, "A3E5D0Z4L63AD8": 893, "A17SNTLDQWMULL": 894, "A3PSZ52D77DM4P": 895, "A18585LWC6ABKV": 896, "A2QO20Z0TAHKTX": 897, "ATWEHBHWFKUSW": 898, "A2OBX89KW06ZPL": 899, "A1BS8VS04EWSWN": 900, "A3QBN0X43PVR13": 901, "A32STGRWB3FI2U": 902, "AS7W26NNLSU8K": 903, "AYJ0U17CIWLM7": 904, "A2GXHAELA9BZQA": 905, "A3JFP1I9GCOM8P": 906, "A2PZSQL3PZPL4Q": 907, "A41II52YCOH8Z": 908, "A240EPDH69W439": 909, "A8M9HVFTJL97C": 910, "A18R90JU5L0P9X": 911, "A2MHKBRV1K48FE": 912, "A1F7OSK6UV1A3C": 913, "A1AZDDFS89QJG3": 914, "A26W1STWGZ0V8J": 915, "AZP8VL10DJLG7": 916, "ANSRHNCQZ67XK": 917, "A3K1ZGGHL4EXU": 918, "A31LLD3KPLPFND": 919, "A17BUSL163PDGQ": 920, "ALH3GV3UKD0BQ": 921, "APYEUSO2BX66E": 922, "A3FP7OTPZKMMZS": 923, "ASYFIB6Z0E8ZF": 924, "AGKYWPUJNOUQ2": 925, "A35SF7WOUI49AM": 926, "A379SJMF93CVYZ": 927, "A58OFA7T7WN9Z": 928, "A3IIQMFNRX6ZTL": 929, "AF3APPUEZ4WU4": 930, "A1R5UF5IOJGWBF": 931, "A17ICF11AQU9B3": 932, "A1O4BH6197KJNE": 933, "AG50D1D7NGIZ2": 934, "A2CYROCBFE8MYP": 935, "A7QILJ0KFTUEF": 936, "A2PR4CK7LT29EV": 937, "AVO94A66EQGFH": 938, "AKXKWI5M5E267": 939, "A3FIGZDJIZU3J0": 940, "A29M9CXOVC4SKI": 941, "A7WLR60DIHE4O": 942, "A26WAE7N3RYJP8": 943, "AX5Y4X8GRVS6V": 944, "A1MRQ8Z7LGQ7N6": 945, "AG2028ZASH070": 946, "A3R8JXBUFRV1LJ": 947, "A31M40X061BW0H": 948, "A3SOJC5EJZP7C6": 949, "A1SS57KI4HA4S2": 950, "A4UZNWPEJ17UW": 951, "AAS4E02BPFAMT": 952, "A18DNSET02IWGK": 953, "A30RJT0XAOY74H": 954, "A3PJJNFE3ZAP76": 955, "A3U19PYYRF7Y1S": 956, "A3W1OO50SSUY8K": 957, "A2GX33X1IV4AUB": 958, "A18B1KJJ14O0TO": 959, "A10S3PNZ5Y0FRT": 960, "A2ZCE0Z5C32X9P": 961, "A2JS5OE7VIGTYS": 962, "A1D6NA1QK3NM5Q": 963, "A2D97LA92PXTNH": 964, "AITKFHF4SYM3J": 965, "A3BMF5MNI9ETXY": 966, "A1G75ZFJMTFRZK": 967, "A2FQ6TUKEETS95": 968, "A2PFKD76DMWIEF": 969, "A2UFVPHIHLKNUA": 970, "A3DLAD4NDHWEDR": 971, "A2KF53C0ETRVEI": 972, "ATLXT64KWUOBN": 973, "A19M8Q3VR3Z3UN": 974, "A10CGTF3GZ2V65": 975, "A2ILV8E3ULQNV5": 976, "AIO1DYYJQVTP6": 977, "A15KYC62I1EIAC": 978, "A1TY0I73S2O3YB": 979, "A2YSQ3GVWYOJDG": 980, "A382QYAWI6F811": 981, "A38ALMKH7U0D6H": 982, "A1ODT2GL0ZA2HH": 983, "A35N0PR2D2QFK7": 984, "A1XZEKTEJFZ3O6": 985, "A3ID3JWCV07D8O": 986, "A217E9YU9PINU0": 987, "ALWVGT9VJ7LS3": 988, "A3IVNKF7B5WUJ8": 989, "A30EXXH5I9GWBF": 990, "A3S34MNS43C213": 991, "AILKG7B84J0TJ": 992, "A2N51AK3OZZOTM": 993, "A361TXVGQDPYUX": 994, "A3CAXDHSC2J86S": 995, "A337MPRLYDSO9C": 996, "A249DTU0E0PWD5": 997, "A3POA5GUWACBD4": 998, "A1FDWNNQ50ATXS": 999, "A2BR8ACW3AVWVA": 1000, "A2FP9UXBM2OBYI": 1001, "A175WOXLHJ9N5G": 1002, "A2TPAF8C8EXPH8": 1003, "A3QXLSQVR1RX5M": 1004, "A7YMD8MSOBO1I": 1005, "AA8TVGYLXMEU7": 1006, "A1K9L49L7HTQJE": 1007, "A39PJ0ZRD3QTLD": 1008, "A2FC2S3PHXDJBC": 1009, "ABS0ZTJI0XVXF": 1010, "A30BXEGRRRJIV8": 1011, "AE2NUFHL35LQD": 1012, "A767RTUPRU4WB": 1013, "A3P89WPE2YL003": 1014, "A1XKUR7RPQ00GN": 1015, "A3G21E26IP4WXB": 1016, "A3DYKR0ZJ7UAIY": 1017, "A1JRIIJV6B9QT7": 1018, "A1H8D53KV0IMX8": 1019, "A2HVR0MZAO14S6": 1020, "ASZ4W6VZD7QO6": 1021, "A11LNPG39A2ZV4": 1022, "A1VUN4JU731CBH": 1023, "A1WIARMTYHFQCO": 1024, "AQK1T1V94EUSP": 1025, "A1DH3QDZX8Z7GO": 1026, "A1L3RWD0VD0A1P": 1027, "A1SG1DJ72ISCRU": 1028, "A2JR5ZTSYSIQYX": 1029, "A234G6UKEMMDCY": 1030, "A30X750M8V1XXW": 1031, "A17IS2KTMUBJ52": 1032, "A1G60ANYI0HMEU": 1033, "A29XI8QYHVHM7B": 1034, "A1EKWMB77ETI3Y": 1035, "A117XUS2KI1M04": 1036, "A3OFOLJN35EQG8": 1037, "A32NZK5H2NIM13": 1038, "A3HGL90C2GYPAR": 1039, "A3MSIMW9K5METI": 1040, "ATLA5CJH0ZZHP": 1041, "A3SFNAMPYLLMIK": 1042, "A2UXYXRUPAO4TC": 1043, "A1UO1V99AK3CS4": 1044, "A1YUL9PCJR3JTY": 1045, "A2WWHOH10OM5OJ": 1046, "AX4M4GN2DLA16": 1047, "A2EHN0WTQ1N90R": 1048, "A1WT5DZYZ10FO9": 1049, "A17Y6O6I2O5S6P": 1050, "A3VPDM6X5UQLR2": 1051, "A1EJJKJJAIZ8N9": 1052, "A16EEZCPYPEUHF": 1053, "A12C1OTJ37UUG7": 1054, "A345JRAM57EGBS": 1055, "A1KHVW4VTZ82XC": 1056, "A2MVSV6ZFK5E2": 1057, "A3HBZYCHTIGP5S": 1058, "A2NY3UM9B2LTOL": 1059, "APR52YKQ7EZVV": 1060, "AV2RWORXTFRJU": 1061, "A4LHEYS82MBPW": 1062, "A3KYQWGVLNDGYV": 1063, "AZ4LR12IMQ36J": 1064, "ATYKIK01AYS7K": 1065, "A14IW8OQ1BS0OB": 1066, "APL83S3QHRHGT": 1067, "A2VXNP8ODTWG7H": 1068, "A2IBUK9XJOYRJW": 1069, "A1SCNB4DE7XPKT": 1070, "A1LUVDJCWYAVUW": 1071, "A1RPR6GIDAA2AH": 1072, "A2U3H8F5V9NPEE": 1073, "A1ILBBI4KFQB7A": 1074, "A27SY1GAE815P8": 1075, "A1GQWYGNTPGFKN": 1076, "A1MNDT4T37NL9V": 1077, "A4LQ2DHV88ZDH": 1078, "A2YBR0BZY6HFPT": 1079, "AS7SVX6IGJ6F0": 1080, "AKAWRH6P6SR4F": 1081, "A3EW0V38Z8JVBI": 1082, "A36VNA9PTF6JER": 1083, "AUXNJSHAU8KIC": 1084, "A31S7BUH1EJKBS": 1085, "A9FHZGXN2PXDF": 1086, "A1I5YAUPX34AOR": 1087, "A3UNR8PMJLC8ER": 1088, "AHKJ8QX765M8Y": 1089, "A3V0AYA9IYS21V": 1090, "A35KHQGVTXKFXG": 1091, "A18L48UCHSWBQF": 1092, "A2KTF3UPWIG1B7": 1093, "AH3QPFU2NYLG7": 1094, "A1YVUUHT093E0K": 1095, "A3D140J4JTAKSZ": 1096, "A3669PE8WMA8NU": 1097, "AW8UW3OFEZR8T": 1098, "A3A5CDA6N3J1HD": 1099, "A1H4347RCYBPRE": 1100, "AAU8IANGH82NP": 1101, "A1JBEME9FKIXQ3": 1102, "A3KHMVKLCRFZB5": 1103, "A1EYDV7OQE5BLC": 1104, "A24OG61UCZF55": 1105, "A1592Z8VTIL15Q": 1106, "AEA9MHUVHG19C": 1107, "A1KGK5825KQBXH": 1108, "A3P1GD23H8E2BY": 1109, "A2HYYF4MR9F89O": 1110, "A3N4R18KX9VISZ": 1111, "A35N3SH07179SH": 1112, "A2SH7OWE8QJYNC": 1113, "A1BCRICL4UUBC6": 1114, "AUDPHTF2KH1JS": 1115, "A1X6ASXO8F7A9E": 1116, "A29DQ5N0LMVP3H": 1117, "A2YUGPUW2HGNCU": 1118, "ABOTQDXWRU51G": 1119, "A5FIJ2TSN0QWZ": 1120, "ADG9G023I0PVZ": 1121, "A1307TZ17X6SD2": 1122, "A2GXAF7Q9OTTIY": 1123, "A21VLPGCRFH6OF": 1124, "A2U64G6KP1ULRB": 1125, "A3T97RJ08ZQ0BT": 1126, "A2VHKUH4DH0F37": 1127, "ABZB6K3IQMXZU": 1128, "A2KUYKZP95RB0F": 1129, "A3V3Q2E70VWCD6": 1130, "A28BR2N16ZMJPT": 1131, "A2H7UOR72X7F2G": 1132, "A38K5XHJ6G5Y16": 1133, "AP5TZGSMF73L": 1134, "A2ILVHWZE9MGYP": 1135, "A2R30QA214XIVX": 1136, "A2STARDV5TN6HO": 1137, "A1UYMA2KBEZJAV": 1138, "AEMTSFFDU85KB": 1139, "AJK65L94VOWHP": 1140, "ADQXQ3AN16RCK": 1141, "A1EDCMHXIMH0DT": 1142, "AVIR4DIQYVIZC": 1143, "A2QVLWFBQ08FYC": 1144, "A2VZJKNHWE9B4N": 1145, "A2Q87SAW72XHBB": 1146, "A2NSKJ0R6AEG0P": 1147, "A3F45B34YOC0QK": 1148, "A13RTK1873ZLFS": 1149, "A1TV61AKAPGSMP": 1150, "AYVE4ULAGMVGT": 1151, "A1WP0CG1OUSHMR": 1152, "A1GED14ZDLSLKU": 1153, "A3R7PGG5QMI6TI": 1154, "A25BQ9WBPFU53O": 1155, "A3H0K82OLZDRDT": 1156, "A3I53LMLZW8GUC": 1157, "A3F8A11FLWKOJS": 1158, "A2N85D8FRR118S": 1159, "A35Y40XVDNIK7Q": 1160, "A3K9PKWXG2J873": 1161, "A26EOYCIOA6JDV": 1162, "A1DCY7A46MU8F4": 1163, "AOUC76JLMBP3I": 1164, "A28DNI5SQT1ITZ": 1165, "A2ZI3U3GV4WV6K": 1166, "A1NQOLKH5T6FOA": 1167, "A1SBUTPIN5HTAD": 1168, "A3COUBI0JP5723": 1169, "A2QHCNJZF3I5K5": 1170, "A1EKCH0FI00Q1J": 1171, "A1SW3YQTS0SWSR": 1172, "A13ARKH8FCOFQ0": 1173, "A3LYHZY1CPSYKA": 1174, "A2CBIGEQKMTZ4O": 1175, "AZ0O1CT77N1W7": 1176, "AS6ZM65L0AG3T": 1177, "A26N3O4QO1GD74": 1178, "A102V8N45CTOIC": 1179, "A1QAPTV4YS16N9": 1180, "A2F5VJBFG0BF0G": 1181, "A3NGK03GOJ1JDQ": 1182, "A1LRQWKGVXCJ7C": 1183, "A20RNDVGF6IOMQ": 1184, "A1STC2PCXN65A1": 1185, "A276HKHAM5VK53": 1186, "A18PENJTHM1SVT": 1187, "AW4K7S5EFQ2MQ": 1188, "APYAPE8TWN8XC": 1189, "AU71YJNA3E3J1": 1190, "A15EREQSX2JBZH": 1191, "ALWI22L1YH50U": 1192, "A3HLZAGW84MWLS": 1193, "A22DAG9I1JESQP": 1194, "AB9LV3BWK3O4K": 1195, "AXYO5J5D0M0SD": 1196, "AANBV13XF1JD4": 1197, "A113DS2A66B9VJ": 1198, "A1FVWVS8CRIRBO": 1199, "A2F239LT1G70GB": 1200, "A17JGEYNQRYMHE": 1201, "A2D9VVQFYQHMUU": 1202, "A2NM6383S01M2N": 1203, "A2F244OGTONA15": 1204, "A3KUVPJHTGGLTB": 1205, "A26AVD5D1SNXIN": 1206, "A2Q582Q4S2MUGM": 1207, "A274YXKOH9OGW6": 1208, "AP3VUC7U6K16M": 1209, "A1S71R4YJDJMAD": 1210, "AAP42A9X4RFOL": 1211, "A363CMKRJ19XHV": 1212, "A2FI3GQHTBZC5": 1213, "A1RXH3XWSYIB1M": 1214, "AS8N98SK8HBMI": 1215, "AZSYHIK3A3KWE": 1216, "A1R2N7UH4YQTN": 1217, "A1VMKL0UTFXJ3V": 1218, "AYR9VFT77U68X": 1219, "AO9G5HQYQHLHP": 1220, "A2ZQFEW8HURDD5": 1221, "AU7VFGP9BGZ0": 1222, "A2VSKUR61RYPYH": 1223, "A1LXM5PZZHTT6W": 1224, "A1IHZ7A10YDVSW": 1225, "A19L0NX40VAU3S": 1226, "A3B3XT2P0I34W4": 1227, "A1R3IUM1KVYK5I": 1228, "A1FT0AWHJQLMJN": 1229, "A2UGQIW2UR9U4K": 1230, "A2LAQ0UNCSXN6I": 1231, "A2B7VGVN59XJUM": 1232, "A2AEHBRCY7G9HE": 1233, "A16467WWAC2UNP": 1234, "A7QQCZK96JMS6": 1235, "A1SXF48MHY0NJK": 1236, "A4O8WIX9NXLEH": 1237, "AYXGSUZEQEIFN": 1238, "A1TZHV7ZF1BP4P": 1239, "A1ZYG2KYW3Q107": 1240, "A32KZUYCAHHU63": 1241, "A21BQ8UAD3D6VJ": 1242, "A3PTW8EKRSZLUR": 1243, "A1WMP19X59ADQS": 1244, "A1H0A35HJMGVKQ": 1245, "A3DES8CHOO4UH0": 1246, "A2UI38UXH48SCX": 1247, "A2WTV2ZI6KWDP5": 1248, "A1D7922BHITJ7X": 1249, "A3UASAIMF2R3QT": 1250, "A38YT9I8SQ20NI": 1251, "A2QB0TIWFCUYIL": 1252, "A1G4KDEM2V5376": 1253, "A32GKT2BDX20YL": 1254, "A21JK1XVN7EDMT": 1255, "A11N2I11HJBD3E": 1256, "A3O4RA4POHFEIQ": 1257, "A1MU2YMN78CADQ": 1258, "A11UJ1CHEHNEGP": 1259, "A31H39YEJEIVHX": 1260, "AJW0OZRACJCP0": 1261, "A1U5JW2BP2DXTZ": 1262, "A8X4UHGLCDNBW": 1263, "A1B1J242B6OQK9": 1264, "A1ENECC591UAIC": 1265, "AIO4X9BRTWT9J": 1266, "A1XQOQ0GWJP1X6": 1267, "AQ8Y0VADON6Z5": 1268, "A2R46TPY466FDC": 1269, "A2H20740ZG3V7U": 1270, "A1A2TYI92R7T86": 1271, "AMXLMG97P1H9F": 1272, "A3JTUS0UZG6V9T": 1273, "A2W959D3BSFS7U": 1274, "A32MQODC8EDEWF": 1275, "A2NH5PVVBWTTQK": 1276, "AUJPT6U07Q5N0": 1277, "A2F8X61SB7F73B": 1278, "A61EY795V8S0B": 1279, "A2FC7HQW52PHE1": 1280, "AP0O3EO7ALT63": 1281, "A3744L2QRP2I8C": 1282, "ASBKP2FY961VO": 1283, "A1CDRFH2UVIDIQ": 1284, "A1SZOLPK06OOTX": 1285, "A1XIKDML1YO1WU": 1286, "A3LQ2OIJG9BO97": 1287, "A1SX73TKLN7DPH": 1288, "AS68XCKL7QZUT": 1289, "A2W23Q4C4EEQ8Z": 1290, "A3EJRWOYRI5N34": 1291, "A1575LB2RX92AW": 1292, "A1WRTQBUNULI0A": 1293, "A1T4SUED31GCHG": 1294, "A2K2XYGCMHNV8C": 1295, "A27MGH8RM9WXT7": 1296, "A3QIK6BB10WYE9": 1297, "A34AQGD2E6H0S7": 1298, "A1R4241KZGQIG4": 1299, "AIC7VZ9VNYRHK": 1300, "A1JUUPJVBDOE3O": 1301, "AL717X1GYM0JV": 1302, "A3CQVSKPTU3PJV": 1303, "A2LOFS1AJM3G6F": 1304, "A2M51VLOW1V1JR": 1305, "AJL25T6NE3RDL": 1306, "A2J6IZXSLF8VB2": 1307, "A1SV13PG7D7SJX": 1308, "A2T0MNN392O3RY": 1309, "A2QWJXBD0LB13A": 1310, "A365807DF8EYTN": 1311, "A2U6LJJO67TRRN": 1312, "A1ZQKZ1K54USYJ": 1313, "A9EN0S3OPP0K0": 1314, "A31I1YHJKPUCAI": 1315, "A3E2U597OBS9ON": 1316, "A2KRRIZVD7QEDG": 1317, "A78Y9O0GSY28T": 1318, "A2CY5UPGEPR12F": 1319, "A1TXHK8MONJHC3": 1320, "A353BBCDJQP4A3": 1321, "A3RIQLKZGBQDOT": 1322, "A13V89Q8UQUKTQ": 1323, "A3HM6KD4JINJN4": 1324, "A1TN2EZ7S2FTH2": 1325, "A3V8ZP41Z782M9": 1326, "A2UISZV5CTD805": 1327, "A1AF9EUGODL08I": 1328, "A3PXFEOWKRCUZX": 1329, "A3S7ZJ0I6KR5H3": 1330, "A3CAYJJALN3CDB": 1331, "A2AV75AK7M1DMW": 1332, "ALM0H3CWDI4O2": 1333, "A3LE7HI0VUFLE3": 1334, "A3847X9XD27OSL": 1335, "A351804L86H9Z6": 1336, "APJDB661HN4UR": 1337, "A3K89V3UFT052K": 1338, "A2IYAPUAR0PTUD": 1339, "A239ER4X93L28K": 1340, "A1BSIL9GW9FCR2": 1341, "A1FOXRAJYN7ZNF": 1342, "A1VZHK5PZJP1YX": 1343, "AY17MGNAV9K1J": 1344, "A33XGGQCEAIBWF": 1345, "AV3A66BTGK2G5": 1346, "A24FOVVEIEAIPK": 1347, "A1GIHV3V7LW85B": 1348, "A3GGOEX6SK1J71": 1349, "A3D7NKLR56DZRA": 1350, "AF6AYACNYZK47": 1351, "AL8FI5X2OD33S": 1352, "A2A9YAF0YD42NS": 1353, "A2EDXS7VPY7L8Q": 1354, "A221FPD86E5O87": 1355, "A3BPZ2XFRLCD1S": 1356, "A2LOCTEN93UHSV": 1357, "A3IUPHLK5U0MVL": 1358, "AWNO50ICXSK88": 1359, "A3GD3SYZUN0FP6": 1360, "AT01W4M7O2N24": 1361, "ALJUE2EBH9XIA": 1362, "A26X49ZG08Z1CI": 1363, "AC7UJP1OQ1T2A": 1364, "A4OTYAYS5X61E": 1365, "A1MUHMPF5XYTAP": 1366, "ASR3LGBNR6FSJ": 1367, "A3PFZA9XC59D2Z": 1368, "A2IOZ71FUD9024": 1369, "A3J1B9AQYC9ZM0": 1370, "A2UXLUXR4XUMEP": 1371, "A1P297U2LS0JHR": 1372, "A2WCNWKJV9DQAB": 1373, "AMS0BR4407K6Z": 1374, "A2W85Q0VJNPYLM": 1375, "AFYLPYJ7AORLR": 1376, "AE4AI4GHFW8PC": 1377, "A2H2K1FKI9COQ6": 1378, "A1E7428658LMTY": 1379, "A2FYOXDW99KK00": 1380, "A13FIFP73X0GTR": 1381, "A2A4IIRGAEXUXC": 1382, "A3EHQECWIRDPZ4": 1383, "A3LKPZO4ZSRC23": 1384, "A2K7N4FBGEHVK9": 1385, "A37BC154GF7ETV": 1386, "A25VWCCTZQ446": 1387, "A2W8NQPP91206I": 1388, "ABTQPLD1K7839": 1389, "A3M1HYKCHSN11D": 1390, "A26EUBG2TMWYFD": 1391, "A9419F2N03T5B": 1392, "ASB37ZYP0PZ0J": 1393, "A22M6JJ3EVP3W7": 1394, "ANJH0FF6IF99G": 1395, "ALD6CN9ZUE7KK": 1396, "A39CGMH5A4XO7Q": 1397, "A2555OR8IRB30S": 1398, "A3NIHCBCOWK4X5": 1399, "AIKJSC2UO4XLQ": 1400, "AM0OKL6AFIBDX": 1401, "AAIMHUYO3NWCX": 1402, "A1FWB3DEF3MTXG": 1403, "A3I9GQ3I0AXL4W": 1404, "A26R3E15OMP52T": 1405, "A225PCLBJLHGEG": 1406, "A2MKKH27I1UU7P": 1407, "AA70TPDCD5D6R": 1408, "A2KOVJ269YNR6M": 1409, "A2IQF36UJM0GMB": 1410, "AMN78P85LBO2A": 1411, "ABX1LE2T3RJJ": 1412, "A3S3Y3HC9BVSMO": 1413, "A0976794S8VOYNT78YEM": 1414, "A2OD11BKV2YNED": 1415, "A34ZOFAJWL9UAM": 1416, "A1M0VRITABSIQ6": 1417, "A29D7CG7TLY35O": 1418, "A1HUO2AXGLYHDI": 1419, "A2UE27NXVYHIP9": 1420, "A35IRTPNXBD1R1": 1421, "A67FOUJLCZPS3": 1422, "A13E7YU3XNRNL9": 1423, "A1P5UV6LO4YC8S": 1424, "A1QU1H8R28NIGX": 1425, "A1GJ1IRDPBQ0DG": 1426, "A1N8QW8DDT7EJH": 1427, "A11EQENJJRH8X6": 1428, "A10VTKMX0HUEJK": 1429, "A32SV7GY4ZEMX1": 1430, "A1RVV44OXXTD0": 1431, "A7ZUY93SQIMVM": 1432, "A28TV838J24262": 1433, "A369YOM4RBUWP4": 1434, "A39X80RZSF8IYF": 1435, "AVFRGWQKCNAR9": 1436, "A1KINZN727NS86": 1437, "A1ITBA90V0EBQ4": 1438, "A3982RSH15PQGZ": 1439, "A2HX3MWQDOM5AZ": 1440, "A3N0KCCCE7E7F5": 1441, "A23VUM4E9BS462": 1442, "A1NH81HVJXIM05": 1443, "A2MWA7HFUXV8J8": 1444, "A2Z886R3GCDYVF": 1445, "A24VYB9EXSWSQI": 1446, "A2S1GTBLVBLEO4": 1447, "A1353000WAKP87": 1448, "A2CGZJXBGSBI0R": 1449, "A39MXA4F9XBI9Y": 1450, "A11F3YONMF67ML": 1451, "AQ5JEZH7VX679": 1452, "A1WOTG0N2J0ZZK": 1453, "A3G9GVHBAHGMUI": 1454, "A25QIF834WW9GQ": 1455, "A1DULQKYC6EV1B": 1456, "AEMYLEFZCRX5S": 1457, "ALBPPZ969I5CM": 1458, "A2JPRGJ2GVDANZ": 1459, "A2FI3GF4Z7QNO": 1460, "A2P652CXM82IH6": 1461, "A3ONDHUXJ0HFYS": 1462, "A3QNL2SYBQ2ZS2": 1463, "A319KAPLOSIDRU": 1464, "A35P9MY9132FNU": 1465, "A2D6BBQ6HFAANH": 1466, "ATSFY4UITEOEJ": 1467, "A2UXU5DDCYN4GP": 1468, "AQGQXINCTPYS5": 1469, "A2AGOAOL5NFEUP": 1470, "A3DZSPA2Y48NMG": 1471, "A2ZF5B40WVBD93": 1472, "A34IE5594AE20I": 1473, "A7KDJ0MVYYRA0": 1474, "AU1I8VGB7D254": 1475, "A2ATHY1VLNANIL": 1476, "A2OWID6GQD7SRM": 1477, "A5T9Z3JIUR0RO": 1478, "A4L7ETIO4IDFC": 1479, "A2Q4BLV4ZEL1KI": 1480, "A330G4U4JWUVJZ": 1481, "A1QGLKV2CITDCF": 1482, "A3GJRZ7FN51LMK": 1483, "AQ7LXULTORIQU": 1484, "AHD4TRX1LXN1": 1485, "A1I3WK7TCIVW26": 1486, "A39LRXD7THXB4B": 1487, "A1A4YGDZRUFQFS": 1488, "A3BGKQY5MNVM8S": 1489, "A3DHWMWIDS2XX5": 1490, "A1HTD9BFY0Y557": 1491, "A1M54LLOTWABKB": 1492, "A1H055LCNXKT1J": 1493, "A1UFPZUUATIGXF": 1494, "A3DSF48FKLK72B": 1495, "AFT0V3RMHG8F5": 1496, "ACPMJP8RVC6TB": 1497, "A2BRTCOIW7TDYK": 1498, "A3QDMBLXIPSVOI": 1499, "A3RDRB33M4U8ZH": 1500, "A1QIH7NR5YZRND": 1501, "A3B15P9JJM9QEL": 1502, "ABU93V5LFXTV1": 1503, "A265TY8TEJ5N8G": 1504, "A29H57JOW1ZB1Z": 1505, "A3HC8CNVGE854X": 1506, "A2DVGHWV0UZLVK": 1507, "A3KHWY7T46BBAP": 1508, "ADYK8EVS9WDB0": 1509, "A22CI1SZBZTN32": 1510, "A18712EH6VCYFP": 1511, "AGRCUD7B2MXPR": 1512, "A23H193P451P74": 1513, "A399EX3UULKLU2": 1514, "AQ63ZV8M31WL3": 1515, "A3HU9KQ2AO7Q22": 1516, "A159B1DZK24I3K": 1517, "A1X1ASMQZESS3Q": 1518, "AL515B28C0GBP": 1519, "A1HW72TSGGCGOZ": 1520, "A3A0F30QQGL1EW": 1521, "A25EMUVX5WMVZ1": 1522, "A2YPX6VJN8LPQZ": 1523, "A9XJ6GVTNDF2X": 1524, "A39A4OQT77H4HX": 1525, "A2GANR9I6XHTU9": 1526, "AVTDFGJK4RSI5": 1527, "AIPGBTM6TJ9IN": 1528, "A1VPZOEEBKTBKU": 1529, "AW189LTU6X9AY": 1530, "A23AH7XNL9GSL1": 1531, "A3JGDBZM9CGRXU": 1532, "AI5LL32JKBN4P": 1533, "A1M07ZN9BP01RY": 1534, "A2JPERAV0416C3": 1535, "APYKGTU0LFICH": 1536, "A8Y0ND4GJJJFL": 1537, "AMSZT5FC3JD5E": 1538, "A1UOP3I8BE70JJ": 1539, "AC5PPX3XLCZN1": 1540, "A3S5LMVBT8ZGWY": 1541, "A2OYNAAZK2PY7V": 1542, "A3Z96U2AVVDJP": 1543, "A14JDMEHQJRR3T": 1544, "A3HY3THGD7ANEV": 1545, "AKF8ZHTJHF9QI": 1546, "A1ARLM4JFWPVOA": 1547, "A2XCWQJ2E8JJ27": 1548, "A1BKFCSK66RF3C": 1549, "A16QJ424UMZVWR": 1550, "A148RQ0M580F8V": 1551, "A24YW6RJPFM7JR": 1552, "AC1U7PPQJKA9D": 1553, "A2I93OMO3ND10J": 1554, "ARP38C8IJIKGQ": 1555, "A2BLBDFMVKAAK": 1556, "AGRNF0GM6NAN7": 1557, "AV37OT7S682UW": 1558, "A1WAA32LZ1488K": 1559, "A1DMRK2YINRC16": 1560, "A2Q2A6JKY95RTP": 1561, "A2LXX47A0KMJVX": 1562, "A25TNBMJ4ZO7RD": 1563, "A27QXQQOLAMRRR": 1564, "A2LTEAUTDYHS85": 1565, "A31EP5ND68247Q": 1566, "A2QVJ11O5ZM9FH": 1567, "A1VWNQOSMPAOAV": 1568, "A2BLA13SDC5T4": 1569, "A3113NZ7WBL3AE": 1570, "A36SXS4ME0K854": 1571, "A1REM7I2ZEE195": 1572, "A3SH6CQYS8FHB": 1573, "A6EKZVZXY6EM0": 1574, "AJI7Q53V06VPR": 1575, "A3DPA9ARQYFJYR": 1576, "A1IFZDSZE0I08V": 1577, "A1V2KI0DASODHP": 1578, "A1WAV1NWCPNI04": 1579, "A33KT5YL805RSN": 1580, "A1EE6LQS3OPY6R": 1581, "AMZCZBK1EF1PV": 1582, "A3AA9BC5QEKHKO": 1583, "A1TZWXI835FHK": 1584, "A3CWEK9HY2VPDL": 1585, "A2HE9UH3LB48RC": 1586, "A6UV1YIY6LVOI": 1587, "A5THJYNHCBX3X": 1588, "A3QNV9LUNM589P": 1589, "A2SSV6KM3W1VFD": 1590, "AC6HYEG9JT441": 1591, "A122SFGLAHQLSJ": 1592, "A2D4FQHV506EPB": 1593, "A32GCOTGFJ9XC3": 1594, "AW4MT9WP95TVD": 1595, "AG8DPYVTLT2C2": 1596, "A2OL0JTU0DLH6B": 1597, "A28WXDXJA1P0MC": 1598, "AOZ2MGUTFOE8U": 1599, "AN0U0GNJJPEUR": 1600, "AG8E2F0G98ZTB": 1601, "A1QXWM5P0CT45": 1602, "A11AP4QERYPCLK": 1603, "ASRCXQORZ246Q": 1604, "A1QBBJ2AHQKEGE": 1605, "AE76U8LPKIO20": 1606, "A2SAH5I8L4JVSW": 1607, "AOWNULF8026F1": 1608, "A37I9VXMBBAADP": 1609, "APVKVOKIUFYTE": 1610, "A2ULTOZBKK4KLH": 1611, "A1V0PVGIZO36BW": 1612, "A3GTZO9OK5E3F3": 1613, "A2I2ZHG8M88CUQ": 1614, "A1TKBDWY45OW3Z": 1615, "AFP6OOD8EDRSP": 1616, "A9VT1JX9I8IR2": 1617, "A1YK1JZXIIMNZK": 1618, "AZIJ44I4NIO5M": 1619, "A2DWCU3P8AEKZP": 1620, "ACRIUHXH5F6V8": 1621, "A3NSTXT3F7CKW8": 1622, "A1T61QP7QHYBRQ": 1623, "A3VBZDYGHF4NK8": 1624, "ABLLHG0REGFX7": 1625, "A3IE8PNBE2LPJE": 1626, "AZA55FJD7CCZN": 1627, "A3JPTQPOKO6TVO": 1628, "A1JISH2AQDW1YW": 1629, "A23OEXX9JTOJZY": 1630, "A2XAQOWHRPY98K": 1631, "A2CISZ4JLKQRJA": 1632, "A7EU2BWLLCJY2": 1633, "AJ329F9H546BM": 1634, "A3CJ7MHAS9IMAM": 1635, "A33UZDO4KB4S0H": 1636, "A2FFWYG9YYZFA5": 1637, "A2LMG36902RJFB": 1638, "AJPAZG1GQX8DY": 1639, "A9O3ZVSNHZ0WJ": 1640, "A2RBZK9UX67328": 1641, "A3T7XVG3AXJF61": 1642, "AH8SVUY191DSF": 1643, "A36BQWQPYU6FRM": 1644, "A2R80172BBNSTA": 1645, "A1ZENB34HH2EIM": 1646, "A2ZHH7AK83JB5G": 1647, "A2VQVI5X3VTDT3": 1648, "AFHYEO3Y1IIDD": 1649, "A1E50L7PCVXLN4": 1650, "A1GUX6R8DV3ZLY": 1651, "A5ZD6FBMZQGDS": 1652, "A1DQHS7MOVYYYA": 1653, "A33230MIA3W7G4": 1654, "A1E7BYP6JGDUHD": 1655, "A1FMWLZ9YY91XI": 1656, "A1VTOFY4N47RGF": 1657, "A2IMGHMF0LO151": 1658, "A171ITAMNOUCY8": 1659, "A29AHSM8RDYA2H": 1660, "A3KEZLJ59C1JVH": 1661, "A2C8N6W0XPYJB0": 1662, "A3U62PW290APHL": 1663, "A2FKC43XAEV54L": 1664, "A1RRMZKOMZ2M7J": 1665, "A3IUW081KXD3PE": 1666, "AJ0VKOMDPHQPM": 1667, "A2E5ZWLVGUV44F": 1668, "A1OWI18MA83CL4": 1669, "A3SVVUZKR2T0VO": 1670, "A28ZOSR4X9V3UF": 1671, "A1E3I2UDK711DH": 1672, "A2F1W17MWJ5E2E": 1673, "A1AN9C4PKJIRVK": 1674, "AUAX1QWUCYKSX": 1675, "ARTHSLN5BW5PW": 1676, "A3ORV1QBL4K9U1": 1677, "A1OPZ3BUTEL47R": 1678, "AJ6H9ZV7TJUUT": 1679, "A3N4CUW4UYC9I3": 1680, "A318IDAWJ9ZYAY": 1681, "A30IP5D5DLHRPA": 1682, "AK7CAW3N1XZV6": 1683, "A3MPHEJ0N39W87": 1684, "A1COPSGCUVZ5OT": 1685, "A3V6APTDD57CRZ": 1686, "AH9VK6BEE5A44": 1687, "A3F8PN1UY4G7ZT": 1688, "A22T6ZBH6C3IY0": 1689, "A11FX8HL2ANK6T": 1690, "A1004703RC79J9": 1691, "AFPTZ4JS6QQKO": 1692, "A2MKJ0Y5DYXXLS": 1693, "A2PDKSRYOJGUGN": 1694, "A1AUMBA4UA4G2Y": 1695, "A1VRPTS2C1ATNJ": 1696, "A14UD72N0L7RXT": 1697, "A16CJ83ZHH89MQ": 1698, "A3LHIRT4SR3F9T": 1699, "A12DQZKRKTNF5E": 1700, "AEQW4I82Z5LR4": 1701, "A13VL2XSHUWRTH": 1702, "A29P9NU4QNFFZL": 1703, "AN33VSFJP6KGL": 1704, "A1BJOD583A031Q": 1705, "AQSHHG42VERLG": 1706, "AFVARCTLZI8SZ": 1707, "A1KI02CUM1WC3W": 1708, "A1BM7SFYKDAHPQ": 1709, "AA0PJWW3EEDZB": 1710, "AGCO9QUESLOQV": 1711, "A27XY27EXTZG28": 1712, "A27HMKOCNPOSCK": 1713, "A1XOLUZP18WVE6": 1714, "AW6J9IILGOZY3": 1715, "A2N7F6VT2SQDYZ": 1716, "A3JUHP1E3WUHEA": 1717, "AIAK483LF8YVH": 1718, "ASL9C4URVKR1J": 1719, "A3GPJER8KNV83N": 1720, "A2D281TRH0IUBL": 1721, "AGXF4W5GTK7MM": 1722, "A192JES8J9ZTKW": 1723, "AY9MMBUKHI2PM": 1724, "ASBSPNY56QD1X": 1725, "A314MIV1UW5O6F": 1726, "AZAE1LVHY66WS": 1727, "A28IBOLVCSQRLQ": 1728, "A19A0NR7MZJ8NW": 1729, "A1GWLTLZCHNEI5": 1730, "A3232H7J6URX9D": 1731, "ARYSDAZNRXN6G": 1732, "A1BKSLDI2V3D5K": 1733, "A2NICGGIGIFU22": 1734, "A1PZ8JEPEX03GD": 1735, "A1YVJ2CLK0L2WR": 1736, "A27B7NWCYVFAM2": 1737, "A2B3A8NQIHITO8": 1738, "A3A90CELVLOUP6": 1739, "A1HOLJW15Q5S5V": 1740, "A2Z2FATA8JNL54": 1741, "A3BVN2QBNPBHCR": 1742, "A2FBPS1P12N24T": 1743, "A1YCV76MUFESR1": 1744, "A3EXIZWHSNVNME": 1745, "A12S8UQEIPZJKE": 1746, "A2701UXI8QGRHE": 1747, "A1ZZR25X0CNOJX": 1748, "A27FP0S5QH7GNE": 1749, "A1EM5OSSM5D1R4": 1750, "A47VUHGWSTDUX": 1751, "A2O9BLNNEAH7JI": 1752, "A2Y9VQ0FGLJHWL": 1753, "AG6TX1ZJHLMO7": 1754, "A34TI7G4IRCORO": 1755, "A3L6DF40IKSIEC": 1756, "A3ITW2IFP6I0NK": 1757, "A3VCQX0VZV9I7L": 1758, "A3HUNHL7WSSVCH": 1759, "A1MD9AEU9C4WJN": 1760, "A3UEQ1CYG8E6D2": 1761, "A2YZGX57M5VNCP": 1762, "A4OVVTZQ4K6YA": 1763, "A5BJMAHZWGJ7N": 1764, "A95FC7Y7GWFK7": 1765, "AYF242R6GQMUP": 1766, "AK8LOFYRZJJW0": 1767, "AG71XMQGQ2UTJ": 1768, "A2UVDPBRZTWN6S": 1769, "A2UT0FWM1DHKFJ": 1770, "A26LD9FQHTM8ZH": 1771, "A1TUV6BBJ96GO1": 1772, "A1JQ00PT7BOTR2": 1773, "A9P07NJ7UV0M": 1774, "A1XCSAX4BRT89Y": 1775, "A8UM78SMPSHC0": 1776, "AKTK11MTN64PL": 1777, "A9XX8OHS2ZQ2X": 1778, "A1OWRLSD7LTSQ9": 1779, "A17AHTCKJ4SUT0": 1780, "A1JAPP1CXRG57A": 1781, "A27R2V3WLS43LP": 1782, "ANYWPIGSTKRO1": 1783, "ADX9NTN40T1HN": 1784, "A35UBZDESLIOHE": 1785, "A2L4LUQCMWBFVO": 1786, "A3DKP8M0GSP8UK": 1787, "A3TJ9NCZKS46LL": 1788, "A2E6Y4DRAY4V33": 1789, "AFR1WVDR88ON2": 1790, "A1Q4M82OFOIN59": 1791, "ATZTIU71681SO": 1792, "A2CWIYIETNBAK3": 1793, "A2VAD79S4A06DD": 1794, "A224O69F7AVXDR": 1795, "A19Z4IDNL1MGG4": 1796, "A1VK6EKINVYAT7": 1797, "A37U4HM0UG7FQ0": 1798, "A3O60C5513YYD6": 1799, "A1O67VSDMVN44C": 1800, "A1AZ8YJTM7JRHL": 1801, "AK5G1G8SD8015": 1802, "A1ZZEEBIQLXM34": 1803, "A3K5FYKXXOHPI5": 1804, "A3UJRNI8UR4871": 1805, "A3U1S5KR287T3I": 1806, "A3TWBW1B17R151": 1807, "A2I05FGBTCRRB8": 1808, "A37USOKUTI724H": 1809, "A2BVNVJOFXGZUB": 1810, "A3U1WPDQLP9CQ": 1811, "A1ZO9D554VQO9F": 1812, "A2IGQTQGWVL230": 1813, "A1PI8VBCXXSGC7": 1814, "A1BK60GZ4QME6I": 1815, "AX52CAV5ICC05": 1816, "AQCQ5F0OJXMG9": 1817, "A35IX2GE0VC0JP": 1818, "A2TO2BN3P4C00L": 1819, "A14MSHFCXPARFS": 1820, "A2HMB1IEBSGSHJ": 1821, "AMNNPDX9MFEUD": 1822, "A15Q9YEG1XPEJN": 1823, "A2ZJMLZ1IA2YA9": 1824, "A17O7FT0JX5B72": 1825, "AN8HTB21NV49Z": 1826, "AWF297MUK3RCS": 1827, "A2K75QOCP9ZHSL": 1828, "AMB5PKU9SN44K": 1829, "A37WA3GUT6N5B2": 1830, "A4IYQHU0L5NZ1": 1831, "A3QZGQGU9XW6RZ": 1832, "A29MA4EBRF6TGH": 1833, "AGKDZXTRUVI2": 1834, "A2NTDBVOZIPYRP": 1835, "A23LTUON8X4G6": 1836, "A1U26DP9DM1JM3": 1837, "AXKYN0CWHATE2": 1838, "A223Y9YQIZWX3Q": 1839, "A23KZ0YXN76OSF": 1840, "A2JX868GM8BRBF": 1841, "A4UWNRY0WWECK": 1842, "A1I06FW4J241AL": 1843, "A31Z48BHHUTB0P": 1844, "A1NX2BNNRZ5SGB": 1845, "A2TZ62B2XCUDON": 1846, "A1564JVII4G8PB": 1847, "A2NT0JP7RW6O38": 1848, "A28T94QB6V54GG": 1849, "A1Z5AB1CVT1DOU": 1850, "ACEJQNX3OQWOH": 1851, "A290I412U46JLA": 1852, "A2YNW0J035DOA4": 1853, "A2LI16D7LHPELG": 1854, "A1QR21ZCQPBKHY": 1855, "A2VWE5SGNDS8HW": 1856, "A2EFIUAOF4YRAN": 1857, "A3CNM18PWKI1Z9": 1858, "A29C0Z6BY8HB9H": 1859, "A3U029B8Z5WGI2": 1860, "A1X2LENOF84LCQ": 1861, "A3M7BCQKSQAK4L": 1862, "A268WAQS5WNMGJ": 1863, "ANEEEFP4BL7ZX": 1864, "A3LF914GG87TWP": 1865, "A21FWV7IMMPSXP": 1866, "A3UKWQS8SRW6IO": 1867, "A11B61QBGHLQDN": 1868, "A34109J1GZMHY1": 1869, "AQTV8CV3NZ06L": 1870, "A2YYXZHT4RHW6Z": 1871, "A2XUTCK61FM8XF": 1872, "A2XB933HCLJU51": 1873, "A1GVJX37TN2KCF": 1874, "A2NQW51T182CSA": 1875, "AWB6LNDICLM3G": 1876, "A3HITJ2O5P12GQ": 1877, "A19NRF4D2F79KE": 1878, "A5T8TXEZREVHL": 1879, "A3TH4UELWBAUWQ": 1880, "AI4JRDD129ZG3": 1881, "A23DE1MPXJQ7AV": 1882, "ARKOOHXBLCOOP": 1883, "A1JH34F5J7AO5G": 1884, "A2X61KKXXR6WNP": 1885, "A2WBEJH71SND3T": 1886, "A3GMVCTJTHYG1F": 1887, "A2NNH35DIY658": 1888, "A194K60CWZ371J": 1889, "A20V7N5A22F4BM": 1890, "A32E70RVY374ZK": 1891, "A33QUFNY4E5D0": 1892, "A1ODOGXEYECQQ8": 1893, "A1EVV74UQYVKRY": 1894, "A1RI2HB6FP80SL": 1895, "A2J0D8EHQBF4KM": 1896, "AJL6HX8O2QLVO": 1897, "AC6LV5D2RKTIR": 1898, "A2TCHXH4SIN2OF": 1899, "AXKNMOECIV3ZA": 1900, "A1EIPS6D0ZZ4UA": 1901, "AJQXRZL67VQG5": 1902, "A3FD5ERJH03DBV": 1903, "A102866V814SOJ": 1904, "A36VNOA1LVRFFJ": 1905, "A2ON6D6P8JM8Z3": 1906, "AJRFZ0VZ0LD26": 1907, "A31RULW0KNYJ5H": 1908, "A1D4OWGUSWO2JA": 1909, "A1GT0G489PONQU": 1910, "A260H97AT6A5LE": 1911, "A1I5A50VXCFJE5": 1912, "A2KZGL8O8ONFXQ": 1913, "A1SB54JRH8B18Y": 1914, "A2OPFLMNQW1YS3": 1915, "A5C06WZPX332Q": 1916, "AFBU9FR12LCYH": 1917, "A3QFINCNHFU3C5": 1918, "A1BAR0DUQ1770Z": 1919, "A1XYATUTPV7MN9": 1920, "A1VPEWW3D9T9SF": 1921, "A12PH6L5QSVTYN": 1922, "A111VACTMOWL5H": 1923, "A3KYZR1T1GN6K9": 1924, "A8BAR8CUBG4SH": 1925, "A4OT65BOPX2BR": 1926, "A1RVM6W2YI7568": 1927, "A3OWOZ8EQGP7G1": 1928, "A23821I9K5RSQI": 1929, "A2NGZRL0T21VIC": 1930, "AVA9W53M34C7I": 1931, "A2AOYMFCNYW14S": 1932, "A2R0Y8W4QCI9Z4": 1933, "A55DD6L83R61T": 1934, "A3TH92GOR6M3RA": 1935, "A107RJ8R12ERDP": 1936, "A2G6YF27Y3NV29": 1937, "A1F9Z42CFF9IAY": 1938, "A9X2MLWQOALBW": 1939, "A1T8FNJK6T5RUP": 1940, "A26EPRAF2EX1SZ": 1941, "A3KDO3XV0MK1GX": 1942, "A396VHMYQHW5KE": 1943, "A1C21QBAZ1W4Z2": 1944, "A37Z3FWDW7JFDI": 1945, "ARPB88E6F2MFR": 1946, "A26CPEEWB2WKRE": 1947, "A1QBOC76MIOJYP": 1948, "A1KXONFPU2XQ5K": 1949, "AYWHCM0TJ4737": 1950, "AUZ3EJAU37NC5": 1951, "A3G5MOHY1U635N": 1952, "A3FC50ZJIT2GMO": 1953, "A1ZV5SF171FFMK": 1954, "A1N2I9XB09TI5Q": 1955, "A1AK356ZAVT3DV": 1956, "AN2CU1YP12J4U": 1957, "A33PVCHCQ2BTN0": 1958, "A34IBXM7E8CPWE": 1959, "ALUV2YKWZENKK": 1960, "A2W2E6BPPYZO0T": 1961, "A356WMSXDZFODL": 1962, "A3B83GRTAX6QOM": 1963, "A1IU7S4HCK1XK0": 1964, "AC24YX9860KDZ": 1965, "A3OXRFCJI67IMN": 1966, "A2LQ1IHTYJEEA6": 1967, "A24H8BVP88VT3N": 1968, "A26CVX8L74IAFS": 1969, "A31Q2I6MYV81OO": 1970, "A260QLS8Z33KCQ": 1971, "A1TH5UXT33E7RC": 1972, "A3N4VTNFPMTHEF": 1973, "A3U5CZ3PV82JXD": 1974, "AYMD77ITD15PT": 1975, "A19FRW264WZTGP": 1976, "A47Q26DA5037K": 1977, "A1VNU6X5JQ2PFH": 1978, "A1DIIT81NK45FS": 1979, "A7P69JYE2TTDX": 1980, "A2I3DSACS5KI6F": 1981, "A179D8LPMCGP9W": 1982, "A37PRC1ARGMA0Q": 1983, "AGZBL86KVR68L": 1984, "A3D0JZ2QXXABQG": 1985, "A2JF04EZ1ASR8M": 1986, "A2LQ1O3IHJQPFF": 1987, "A1B5KI7110XHWI": 1988, "A27S0857EIIG8W": 1989, "A3DFH4CKPIT0N9": 1990, "A22E56DQ8FTP36": 1991, "A3LDLV1GWQJLEQ": 1992, "A1E5WXNTI7EO2A": 1993, "A2WB7LZ595CR50": 1994, "A1MAI0TUIM3R2X": 1995, "AWXQORMZ3JY4P": 1996, "A264B6IZKTH2QU": 1997, "A27FYI2VCJR3MN": 1998, "A235NA61RC6YC1": 1999, "A3QJU4FEN8PQSZ": 2000, "AOAOARIH72UWI": 2001, "A14E7LZASLSX36": 2002, "AL1708MTIB1MD": 2003, "A19YOYY7FLQMA6": 2004, "A35Y0RSU09ANEN": 2005, "A2CRIQOX1SYA3I": 2006, "A39BGN8JA7CIFX": 2007, "ADY836HK6QSYR": 2008, "A1IA0O3OYQO9LV": 2009, "A26JLTTRXIY6OI": 2010, "A1P77JG6PMRRPK": 2011, "A15T487HNTIOF7": 2012, "A26AVNPH90LEIL": 2013, "A3KPR2UOBT0O2": 2014, "A1RSBRZQ8NXCSM": 2015, "A1INP6SE3454WR": 2016, "AI36ONYG96EM9": 2017, "A3LT1JEFWX443A": 2018, "A367W4LQ54FYX1": 2019, "A2W2UAOHUVBZIX": 2020, "A3HJ51898Y45PQ": 2021, "A1DF11QTXYYVLX": 2022, "A3BN5Z996H9TZQ": 2023, "AOT6PL9L9GQP3": 2024, "A3M4C8M5J5C5T3": 2025, "AWBBFXTYT2ZNA": 2026, "A2OZNDNYUJIV25": 2027, "A3F2GE88HD8MDC": 2028, "ACUL2NEZAYUNG": 2029, "AMK5PCBGAEW31": 2030, "AIIR8E34EDKCQ": 2031, "A2UQYZCO6C3IU2": 2032, "ALQGOMOY1F5X9": 2033, "A2Y4S4CNGKF21S": 2034, "A3MW6AIZWLJCOO": 2035, "A1TRAEV7QWA5DX": 2036, "A35LT14WG5BX0T": 2037, "A3MFGULNTMAJS9": 2038, "AOCMIJP3EHBNR": 2039, "A22GY8IOSBB9BG": 2040, "A5H8NA5CJ0FK4": 2041, "A3AUM2L4PLIEML": 2042, "A31JL4CDCBXIPX": 2043, "A31HN9K3QEKJF3": 2044, "A2S4OPKLE5FB7X": 2045, "A1OOJZDRA523XB": 2046, "A3C0NM5PAFH2MB": 2047, "A15S9RB0R1D15Y": 2048, "A3O7EIHOFHP6N3": 2049, "A1OPP29TD7SIQ9": 2050, "APG4YVSUN3T6S": 2051, "A1M04H40ZVGWVG": 2052, "A2GFX3DQ8ZHPVK": 2053, "ATYL6HLA621R4": 2054, "A2GI8X394RLF83": 2055, "A2B04GUVF48WU": 2056, "A16ZKKJHDWC44Y": 2057, "A38KO3KKR7GF4V": 2058, "AB24Z8PTNQ33I": 2059, "AQ5WRR4MS98YZ": 2060, "A3FPHTS8Y0ND6X": 2061, "A1ZBJ03O1D78CS": 2062, "ATDE9JYCPI0L1": 2063, "A1JZFGZEZVWQPY": 2064, "AU0LLORGK9IDR": 2065, "A1JTTI1KH3DOCY": 2066, "ADYZOSTF9LZLD": 2067, "A3MQ15651KGVLJ": 2068, "A2EXGRAA6QW96Z": 2069, "A2V0I904FH7ABY": 2070, "A1ZPY91VE3IDN1": 2071, "A1JH23815DVN5K": 2072, "A2XRSLJ5U169XP": 2073, "A4Z5J9NAHEHDA": 2074, "A2G70Q3AE4Z8LJ": 2075, "A6WJQ1C01N36K": 2076, "A28Q9KZGZEDKTZ": 2077, "A21DO3PPOL66R0": 2078, "A2HSF1ZJGUQ54J": 2079, "AC5DFMPT2E0K2": 2080, "A2VC48WIMY6L6E": 2081, "A264H93IURWMJR": 2082, "A38QHZEEYZKT27": 2083, "A24FY1EBJ7EWLH": 2084, "A1GMN83QQJ5K53": 2085, "AYQ14XGJODM9J": 2086, "A1ER4AGDHQUXYV": 2087, "A1047EDJ84IMAS": 2088, "A2M7F89YZJBD6M": 2089, "A33B0FFULH1R12": 2090, "A1GNYV0RA0EQSS": 2091, "A3M8R4JD1SIS76": 2092, "A2705TYWNRS495": 2093, "A15T9G38F589KM": 2094, "A3UZT4PB5SKD2H": 2095, "A2PUKFH7AJPAC": 2096, "AWJMRX99ITPXK": 2097, "A30ILEZYINVDB": 2098, "A5A3C6XVDYUND": 2099, "A1437CAM9CNC1E": 2100, "A2YISOGM55E9NG": 2101, "A339CCNJEZ2E1K": 2102, "A6LPHO95P3540": 2103, "A9HCLHLFHKS2H": 2104, "A3U62H044GZU7I": 2105, "A18OT5BHCTEFDP": 2106, "A1NZET944GAD05": 2107, "ABRT2IMX0FIS": 2108, "A2IDMQ1TTPJHNK": 2109, "ALDKBXKQW78KI": 2110, "A2S8B0NT5TYY2P": 2111, "A5DI519SEY4A1": 2112, "A1P66GJ6VSS2E2": 2113, "A30M2N0ADFINLA": 2114, "A2HNK6QXJFXCL2": 2115, "A6CU6EKF6M5LY": 2116, "A1T71T5GUD8FJ3": 2117, "A593D8BBKM43N": 2118, "A2KLA8YX8P7PCW": 2119, "AZGWBAQ061SBA": 2120, "A2K7JNTNYAVGVZ": 2121, "AQJ6FUQ7BLW3A": 2122, "A3PD8KD87AXNLD": 2123, "API1QT8CGQKRI": 2124, "AHN5NY7E8XCQ8": 2125, "A2W23UG0TUP3A9": 2126, "A1G0ONAQOERNXS": 2127, "A1M3JZ6SLJ4F4B": 2128, "A22B7FDW1IG1C6": 2129, "A1YOWWJOPO6HUO": 2130, "A2LMQA2P6GNYQO": 2131, "AO9XCS3PV5MXK": 2132, "A36TZW2R417CNK": 2133, "A3J14WG9NIQBI8": 2134, "A1DGOKPBIEAM3U": 2135, "A3FAM6M9DMUAMB": 2136, "A3V6BY9QDMXND7": 2137, "ADUHM8KDWZCWK": 2138, "ALYWKJYXJ6W5X": 2139, "A1SIXOUI2382TE": 2140, "A3M77RHH1DLIXD": 2141, "A3HVX4YYJLXAFD": 2142, "A1OQDKUA4PTVJI": 2143, "A3EDFZ7K9VRI3M": 2144, "A1AUVLXU2XWNJ1": 2145, "A2D92SFTNPSM97": 2146, "A3SVOS1EM9RHCX": 2147, "A2UDWSB9IU25EN": 2148, "A14ZXOYLX5LVH3": 2149, "A34SQMSWWKU189": 2150, "ADCFYDFH76H20": 2151, "A26VG3N0GDDHFR": 2152, "A2VQEJB0T6T7MB": 2153, "A1QYE76M7E4ZK4": 2154, "A33PKT5CAKBX1D": 2155, "A1E2LPIGID4OY": 2156, "A2J1S0OK8OEHI2": 2157, "A2XQHW2ZLE6IHQ": 2158, "A2XJXPYLCQ6TMS": 2159, "A2OZ4794P16TU1": 2160, "A1CO2F7VSQ38W1": 2161, "A1DMSC136B37NO": 2162, "A3GRPCW9DG427Z": 2163, "A12LOSDZX5869M": 2164, "A2QBQ87U1ICV4G": 2165, "A3FD8YGYYM5GHV": 2166, "A33F2N4Z9GK7UE": 2167, "A1MOHHZ5ZSQCRD": 2168, "A1BCIXUOEVOS73": 2169, "A3BYZUURF9LNYQ": 2170, "A2QOVJGC3TGEAE": 2171, "A27UCU6Y2I6527": 2172, "A3SA32FKK53HPN": 2173, "A15TT902PJFJ9C": 2174, "A1OUF3DPG2PY1X": 2175, "APDRTZZZ13HUM": 2176, "AUDTWMXQAVK98": 2177, "A2JZ8T64YZDQSI": 2178, "A1X2B7H1P11DXH": 2179, "A6VPK7X53QNAQ": 2180, "A173YMJ9XFVRSY": 2181, "A1I6U5AQAT3ZG9": 2182, "AKJHHD5VEH7VG": 2183, "A1BDARA133DP91": 2184, "A3F2926FPOBNL": 2185, "A1FDSZISWIXH1A": 2186, "A3M16JSEXT9IKR": 2187, "A2QDOJFFLFGF18": 2188, "A2V9DTXTQ5YIMK": 2189, "A2I5QH4F5FDKK5": 2190, "A2TXMYYGSZCSZ1": 2191, "A1AG7F4Z1EOO5L": 2192, "A3R5GTYQ50QVMD": 2193, "A1EWZC0LM7TTSZ": 2194, "A1ER643CCBZNSB": 2195, "AY4ZDVSY3VXP8": 2196, "A1JOSG34UV7LK7": 2197, "A2MXNH5CYUBMAS": 2198, "A1Y7P7UU6XH1Z5": 2199, "A2MSQNPTNAAGL1": 2200, "A12ENBT314RFXR": 2201, "A25C5MVVCIYT5D": 2202, "A1YX6S4I5GG5VK": 2203, "AMCAID3LTHKEC": 2204, "A4SD8F79JBYG2": 2205, "A17771LTRWSKQ5": 2206, "A1WH5J3AP5JR7H": 2207, "A276IP2VUGOSIJ": 2208, "A51PAISHH32ZY": 2209, "A8GV08VRRXTFZ": 2210, "A2349I3TN1EX38": 2211, "A2CGIR426NCD3U": 2212, "A24J358C0ZCFLY": 2213, "A2KTNK64VDJGJ": 2214, "A18JAF91FTLN9H": 2215, "ANM9LSZS7C67V": 2216, "A3EAP2VG0BVYWX": 2217, "A11GP02YZJBGG3": 2218, "A2B7XFLCD0N7I1": 2219, "A3IA9CPZXMBEYC": 2220, "ASDL3MQQQXTZX": 2221, "A2EWHC4E4NJWMI": 2222, "A2Z2LWDTHN2RKY": 2223, "A1Q19LUA075AOM": 2224, "A3VGHF7VNFBMCQ": 2225, "AIY1U7FDL2L8G": 2226, "A1JDORTDBL9BJE": 2227, "A7O99EO1W25PC": 2228, "A898MSI4C3E4B": 2229, "A35EYM5A6DJ713": 2230, "A3SXKZ1Y3SGW3Q": 2231, "A1832G4GPDDPOH": 2232, "A2NWUUABKJ8OAK": 2233, "A1XGSMXS6SEL77": 2234, "A2LV8HCYHEMQ0K": 2235, "A3RV9I6P9O0T50": 2236, "A13OUY99ND8NWI": 2237, "AL3S5XSYS4ZHX": 2238, "A1XQOAMM9F7LGP": 2239, "A2XKJ1KX6XUHYP": 2240, "A37NYXQ098PPIQ": 2241, "AKL16UM40HCXQ": 2242, "A17PDN3EW1F05G": 2243, "A117FS98WND9A3": 2244, "AQH9RP7JAVY1C": 2245, "A14NOLEEBDE2Y9": 2246, "A1L1AJ8459YJXS": 2247, "A27V5FYTO651JT": 2248, "AWZ8DBLGVO60X": 2249, "A31LB1IX6EDG3X": 2250, "A2Z4S1H1X5BIOX": 2251, "A2OUCP7JHXG9P9": 2252, "A1BYTWH89FG52O": 2253, "A2PLHVWJ8AMYJA": 2254, "A2LO9WPU56M37R": 2255, "A2EYTFKG1JSXEQ": 2256, "A337TR2I6J5UVE": 2257, "A169OY1LOA0RX3": 2258, "A1CYV9CR67GKU0": 2259, "A2BS9MY35UH0LK": 2260, "A3DIJAXX4S4C49": 2261, "A27JPD9Y6H9WQK": 2262, "A1WMT21SRY3W5J": 2263, "A3AZI828WJN1CD": 2264, "A14E1OFMG2FCZG": 2265, "AXWSUELYCAPC9": 2266, "A1VOVGNX054PQC": 2267, "A317RWPY08I5QX": 2268, "A21ZXKN8Q0UYJV": 2269, "A3C95L8JUAL3JT": 2270, "A21TJVRUHT41X": 2271, "A27W7VY46CE1I1": 2272, "A1BH1VKHCYHGPR": 2273, "A9BM5GD4ASCMD": 2274, "A3NU2R1I3BJND3": 2275, "A1IMVY2I2FO0WY": 2276, "A2Y3RNMBWIIE5F": 2277, "AWNY6WM2NJZD9": 2278, "A2JFUJ4TLYXH0L": 2279, "A2IDRAYYZ5GKBZ": 2280, "A3SE4NU7AGO47Q": 2281, "A58N07M0ZCYMB": 2282, "A4ETDBJYSJEUZ": 2283, "A1HD0BF7SJH4CG": 2284, "A3U5MO392GEEH1": 2285, "A35GHFPOGAM6YJ": 2286, "A1CSFIQ41U5FWY": 2287, "AM3Y7XXIDRUPI": 2288, "A2M8A83NWTB9TB": 2289, "A1MM6KZOJ61TTR": 2290, "A3PLQMGW6OHR6R": 2291, "A1VN06K4Y0I1Q0": 2292, "A1A8RXQ55UA8XH": 2293, "A1G2SRMY3SCI5M": 2294, "A342YY7GHWRUYC": 2295, "A1VSTIE4LDB43M": 2296, "A9BBI78B2ZDVP": 2297, "A21P8RKP4HRO1W": 2298, "A1VTBADV3JS1EC": 2299, "A2PMR2PIGWKCQ9": 2300, "A1QT3N5FUQ4I47": 2301, "A1LA4K5JF78BER": 2302, "A1Y64EPRAH20CX": 2303, "ASFW4ZMNZJKDA": 2304, "A3THYM7XMB8B0U": 2305, "A1OA65HXZIINHR": 2306, "A217CC8F7N5717": 2307, "A1EGCED01USBA9": 2308, "A27BN4XUMKEBW6": 2309, "A13HG7EAUWRYPP": 2310, "AL9KKQ4V6EQ1L": 2311, "A1X2200VP4P4U3": 2312, "A1GF1J6Q9ERSMP": 2313, "ANR73TPVBCQ9K": 2314, "A3BJ0SU5CRQA3C": 2315, "AMUP8DYE7EAN2": 2316, "A33B3XCIXB4ZVG": 2317, "AUCXT9K30SHYF": 2318, "A2NML53YCHS80S": 2319, "A2TOPNOYV52Q8K": 2320, "A1OF72PQR4MII1": 2321, "A3CHMHGSJSQ02J": 2322, "A319Y83RT0MRVR": 2323, "AAZ5OJ2OOJ2DK": 2324, "ABCNO99OFECJ0": 2325, "AW7BIYHXUIZ62": 2326, "A1NXA6Y1T9XDUM": 2327, "A6X1O3A5C5FX1": 2328, "A3RGYUK1MO9V8E": 2329, "AHYCDH7T6CC6E": 2330, "A36OW4CTHS3CCJ": 2331, "AP2GYIQS95NZG": 2332, "A1B6O7SAIYG2N0": 2333, "A1GQAKL9CGQLP1": 2334, "A1IHK8GL1ESOND": 2335, "A3T7V207KRDE2O": 2336, "AOPXAQV9GT9XO": 2337, "A397CWU6DM3O5G": 2338, "APMJZGHOHGXY9": 2339, "A3P9D22KDEXVMN": 2340, "A35OQ90FU3P52": 2341, "A1V1EP514B5H7Y": 2342, "AZQKNX6F8S84Q": 2343, "A23GFTVIETX7DS": 2344, "A2AF225HOH0CV0": 2345, "A11LZPM3Z86VWM": 2346, "A2JDVZNTCXKUS2": 2347, "AM83WJG9BE2EP": 2348, "A2OWR5G2OAQF7C": 2349, "A12X7K54734QXE": 2350, "A30ODR6WBE61UB": 2351, "A11F5KW6QXHL8L": 2352, "A2HNOQBIAAOZU": 2353, "A2Q8GFSEUSGJ51": 2354, "A23P5BO1UGNIRR": 2355, "A27FG9YUBFDU2S": 2356, "ALYZJ7W14YS26": 2357, "A312UBIOP091MH": 2358, "A31DVKL8JE4XAH": 2359, "A7EK88GF8N40F": 2360, "ALGI34BYWIXZG": 2361, "A2WC9NFLG57W4H": 2362, "A2CF66KIQ3RKX3": 2363, "A28N2AWOVO2PB": 2364, "A1LG1DKUZXGJ6J": 2365, "A25NCR4LJ62EZN": 2366, "AQ6AGWKWMTY8H": 2367, "AFYQ9V4XBVCJ1": 2368, "A1GWG5CWLKJ7ET": 2369, "A34W7QA4J5UTOR": 2370, "A3I5YPJZMTG1QO": 2371, "ALBW2ZBS6Z2AY": 2372, "AMLA0B6EHD4OS": 2373, "A3PEOF0GX4EN38": 2374, "AR9GZ8B7NJJPN": 2375, "A3UU8O0Q7TNWPH": 2376, "A10QJ6CMP3UHC6": 2377, "AIWNA9CO69GZT": 2378, "A1OKEF8X7C0T45": 2379, "A1H9TJEG3YPZ3M": 2380, "AWFY5DWAOFBD6": 2381, "A10NK3J44E66BN": 2382, "A2PL0US7RN67G": 2383, "AY6A8KPYCE6B0": 2384, "A1SXCGBJ9JW2MO": 2385, "ALCLEF26KV34M": 2386, "A2XAKGRUHIE2ZA": 2387, "A16YMCFWGSFGS9": 2388, "A1W6PXDD1CVKI": 2389, "A3XAKONHKWYC4": 2390, "A12V2M84DUFGL5": 2391, "AEZ3UJ35FHPHL": 2392, "A1YNLNPKDTFH5T": 2393, "AUECZWVG4X7XK": 2394, "A1N5KKDDOI2OAJ": 2395, "A1U5D2G92QYD7Q": 2396, "A20VAHDMLHVWG1": 2397, "A3N8GVI3OM55DP": 2398, "A2M7J5RHF69TWH": 2399, "A88H8HDPWVVMG": 2400, "A3MSHV2DCAE2MD": 2401, "A1DYNEMS8PB7X4": 2402, "AU2EBC2WHIO7P": 2403, "A37IRE9GZ0CZ7I": 2404, "A1KWIAKMANZVIV": 2405, "A1CYO1O606T8WA": 2406, "A168SCI9KUMXD9": 2407, "A2L5MYCFKKME3": 2408, "A24X2NYEX5WAS4": 2409, "A1SKPIJNE036J3": 2410, "AYGEP8I4BQ3CK": 2411, "A2IACU8LJ1FCKE": 2412, "A2WB4OWBUH2VQX": 2413, "A257XGMVGITLCT": 2414, "A2AF0NOCM71J0B": 2415, "A3TJSWA0W9ITYE": 2416, "AR3EVUQF0AC7R": 2417, "A1QK0XCAPHIW1L": 2418, "A1DES1NRVS4X5H": 2419, "A236RYWNTAABDC": 2420, "A1F1SGYXCMVHF4": 2421, "A1K35ZITHQS8RR": 2422, "ALXJJVFS3ZKD6": 2423, "A169O5HY388HQN": 2424, "A1XDQFM10Q1SMK": 2425, "AH1WO4RD371X": 2426, "A1YPT5II83LY3I": 2427, "A1JMYG5MOYGDYJ": 2428, "A1Y7C52533BA2H": 2429, "A29JF6QMVW3XDD": 2430, "A1UBGDI1IIRI75": 2431, "A3J4GX5IY716PR": 2432, "A2R44UZ6Z9UOZP": 2433, "A1X3ESYZ79H59E": 2434, "A16Z2OECAUX8Z4": 2435, "A1M5ZT35YX6TIN": 2436, "A4EBYIKOMYFF9": 2437, "A2P739KOM4U5JB": 2438, "A244CRJ2QSVLZ4": 2439, "A1RIBFSYNG0DQE": 2440, "A1D0YC94ZS5CNO": 2441, "AAGQNG7TITMMX": 2442, "A2086XXFX0M0L4": 2443, "A2F6G3JZNTCNC1": 2444, "A18PFXJ4QPTSX3": 2445, "A1JZ0AKAMW0MXM": 2446, "ANBCBZIDZ9XNL": 2447, "A1LANNQ26C7MUT": 2448, "ARO9A0ZAZGC4N": 2449, "A3RALES3RIRVH6": 2450, "A2SB4RX7OJ43I": 2451, "A1OFV9Y06XC76K": 2452, "AP6U9UC7P8ZUR": 2453, "A1H9ASP5TUCSP9": 2454, "A9OVI9QXVG3J0": 2455, "A14OV0HV6TRWFF": 2456, "A16BMPHP8GSIWS": 2457, "A1PNPESTNPTK4E": 2458, "A1RXG5MXNYPBKJ": 2459, "A1P6GN2K66B1W5": 2460, "A37Z9PFALNA9V5": 2461, "A2DQGD2M6EZRS6": 2462, "A1UHKF1UQ3EGW4": 2463, "A2F0E69BAX0T0T": 2464, "A2OX234OSU0SD1": 2465, "A1UYMXFON06KQ6": 2466, "A2WUHKA1I75SL3": 2467, "A27CTW0GPEE0AZ": 2468, "A3B9C6MZAFC1JX": 2469, "A24YNYNC6QJNBN": 2470, "A1SD1T5VZXUAS6": 2471, "ARC8GAY34APCD": 2472, "A25N6AYW8BTYBI": 2473, "A2II9R80CCT0VK": 2474, "A1J5HIF41ENSMZ": 2475, "A26UNIPEVYE9DE": 2476, "A2C53KWA8VVBM4": 2477, "ACREHLVRC4H5B": 2478, "A2KO6M61XQQVCU": 2479, "A335GUD1YBS31U": 2480, "A2MJ8OL2FYN7CW": 2481, "AX329NHW6B7BA": 2482, "A93GW5XX51MAP": 2483, "AQIBFWWA8UWKF": 2484, "A5H86XYSS0OU6": 2485, "A1M3CSHV1X9PAS": 2486, "A2X3ZCTZ6PUHMC": 2487, "A279A4Y2N1CQ26": 2488, "A7C77J4MH94B6": 2489, "A1Y39T2CT36YL0": 2490, "A2K4MXD1N2LFJB": 2491, "A259HHYBP6ZNJ3": 2492, "AY1EF0GOH80EK": 2493, "A16YU3GRGCD95S": 2494, "A3CBCVHIK3G76X": 2495, "A2XIOXRRYX0KZY": 2496, "ATANE2SC44592": 2497, "A1XJOSJN6FHFO0": 2498, "A2J8289OOT5DE4": 2499, "A1989WJVG7DHBK": 2500, "A209XHC20QAYM": 2501, "A2FEM4XI55SY0W": 2502, "A34T6SD5HUGLCJ": 2503, "AXNJFYJRDK7CJ": 2504, "AR74YY08IP2WE": 2505, "APCSV85SWASN2": 2506, "A210SPRGOOG2D0": 2507, "A307YFSORUAXSQ": 2508, "A3N876BDAQGWOU": 2509, "A29M09QBG9TZLP": 2510, "AIYGTPLDBNVDP": 2511, "A2V55J9CCQCOG0": 2512, "A1BEKAQQGP8CMF": 2513, "A2H667ZUNLNTF1": 2514, "ARWZ17IPLQ81": 2515, "A3FA5DUFXCD4WE": 2516, "A1ZJGTGZU816H3": 2517, "A2PU5BCS7PLPZM": 2518, "A2TKCAO7MURH3": 2519, "AOPZR9IDU2JV8": 2520, "A2OJCTT5WLB2HR": 2521, "A3Q2CITG3XZ7VW": 2522, "A33J61NHIEW31F": 2523, "A339NZQKH84XZG": 2524, "A69FYNS72Z43I": 2525, "A2P6QV3P7ENWPR": 2526, "A2SQHL9G03ITMO": 2527, "A1GN2XQI7L4QK4": 2528, "A35V906GNOVU3L": 2529, "AMYLE2O84OB93": 2530, "AON853FSY8RNJ": 2531, "AM1S1JFTOXZMJ": 2532, "A2AGBL998D0FYY": 2533, "A17E3NBADNTI3X": 2534, "A1KEK09ZA6J9P8": 2535, "A2O0ZDILYOJP6W": 2536, "A2ZWTFZRNQW7D5": 2537, "A13H5US9Z7L9M7": 2538, "AKE6DXEN3GWPC": 2539, "A2E0TJ49NACDBA": 2540, "ANKQGTXHREOI5": 2541, "A3AHDR4F2J7YXX": 2542, "A1ZVMTIRYZQDL4": 2543, "ADLVFFE4VBT8": 2544, "A2WE93LJX8PMT1": 2545, "A2JFL163HUJZG3": 2546, "A2CZPM110DW516": 2547, "ABF0ARHORHUUC": 2548, "A16PUD6V3KAZ0Q": 2549, "AZYJE40XW6MFG": 2550, "A2KUUIJ52MWDAS": 2551, "A2G9UDL72YUTT8": 2552, "ANVPLS56WCKL2": 2553, "A3A5XNAM3ZW7Z6": 2554, "A1GYEGLX3P2Y7P": 2555, "A28I19Q54MYXGV": 2556, "AT1RF4WNPGGLC": 2557, "A1BT6TL7UCIC5Y": 2558, "A11IKWE7B29TOJ": 2559, "A2GOHBNQ58WOKC": 2560, "AO7RFXGXSY3LN": 2561, "A1RNPRQWJNU7G6": 2562, "A1MQK7QV7RVB83": 2563, "A32OWCGEXIE1EI": 2564, "A3KDU6P6JM1ONO": 2565, "A20K4RKCF1VOK3": 2566, "A2T006AT1GONGJ": 2567, "A16R6O1P7TMF9N": 2568, "A1G1TLVSFCIR0P": 2569, "A1H0O2ATHZHTRP": 2570, "A2HDCO3BL326PC": 2571, "A2TFOVAWNSEB4X": 2572, "AH7SGI37JSCHK": 2573, "A2A84ELV7V9NSP": 2574, "A1F0WYFGJMSMLK": 2575, "AU6OQZPM195YO": 2576, "A22HY3D260KUAW": 2577, "A3OALG3ADDM5US": 2578, "A24ML2IO9G97EK": 2579, "A2DWDFZI4DUW3V": 2580, "A31FNX12D7CPFU": 2581, "A3L0V7BHQVBXTB": 2582, "A3OWFKDYCCHA75": 2583, "AISGAKMBB5HBY": 2584, "A2AXSSH3OF06GS": 2585, "AY3VKPCPKXOD9": 2586, "A2628GRX57R8KV": 2587, "A2IYG58AN2OOXR": 2588, "A30NNR68JX22K0": 2589, "A25FFEKDGM7F1G": 2590, "A3E8AHUAQEX0QH": 2591, "AXHETL0M8XZPT": 2592, "AP8MT8DWI8K0G": 2593, "A2BPHU52JE21J3": 2594, "A39JGASUME7CAJ": 2595, "A3NYZVVRN7272S": 2596, "A1AHNV14W10S0X": 2597, "AI3Q9MPO6Z7LR": 2598, "A1EQVPJ3O3PE7M": 2599, "A2OI72C1Y0GUD4": 2600, "A2HND0E9TV3T78": 2601, "A26JQI6AC1C588": 2602, "A3KUYNSTZ6TN38": 2603, "A1VNXM9E5MSS9A": 2604, "A3IXMUXE13KALF": 2605, "A31CR1WOVCML1Y": 2606, "A3O74KHNOA8NGB": 2607, "A39DIJK69CMNHP": 2608, "A11JXAJHP7KESY": 2609, "A19QPJNL5HOJAL": 2610, "A1ZEJOWDQ3YD43": 2611, "A3F9CMU8KNAY1M": 2612, "A1ZAUB7IKXDVKG": 2613, "A17RWH6Y9DDYBR": 2614, "ALPX3MQ4JK9TN": 2615, "A26BC445Y8S54S": 2616, "ABCIUE6NUFKSO": 2617, "A3HDIZAWPFGVWG": 2618, "AOE6HAVFCJSLY": 2619, "A1BRQO2VLX0QVW": 2620, "A2XI3URIX4E0PI": 2621, "A3PDFABEHP9FLP": 2622, "A34ROSQ0940HSD": 2623, "A1TURBPBTDENDB": 2624, "A29ZVXI6OJ87RO": 2625, "A23IYYD1CN8O86": 2626, "AZKDRBREVS7WU": 2627, "A15TM51XDDGPZ7": 2628, "A30AOUCBJL8OZ3": 2629, "A1LE5PV7Y0I0T3": 2630, "A2UAAFVJ05HSAX": 2631, "A35K19WU9EGZDI": 2632, "A1T0NEGC9YQPR6": 2633, "AAC01CP4YYPPF": 2634, "A3D5IBYSLHNMYA": 2635, "AL60IYEBZEAKK": 2636, "A2DUS24FBC9FH5": 2637, "A2YSCGRGHNM8BZ": 2638, "A3U8F6TD23XIEY": 2639, "A2SDNB5E6RAI0E": 2640, "A2ZMNQ7UMOIL8W": 2641, "A2E5YIM6TXUGCW": 2642, "AC8PTTE9SEU9E": 2643, "A3G7ALTTF642PS": 2644, "A3NL3JCYZJ8IIT": 2645, "A37UX46Q3OVSAC": 2646, "A2NWGJDNN7TG1H": 2647, "A3W061W4O0LMU6": 2648, "A3UYU1NY2CCW2H": 2649, "AM5G0RHY51UJV": 2650, "A3R36L6I3O8HNM": 2651, "A2DIYQC8MNVYUB": 2652, "A3UPYGJKZ0XTU4": 2653, "A3T1HGP5MN7OB6": 2654, "A2P0R91RPQWTJG": 2655, "A2QU87AQAH6S5H": 2656, "A70NFM6KHU24F": 2657, "A3FD3BHIUYIFPD": 2658, "A2L6QS8SVHT9RG": 2659, "A2KWQ64TRHB3YH": 2660, "A2UNEEEJNHGS2D": 2661, "A1DTCJV6KOMJOA": 2662, "A27H0T39U3FZB5": 2663, "A1DFL66IDY0Z2Z": 2664, "A3MFU0GVZUVH3K": 2665, "A3H5QGH5OD2XGX": 2666, "A221I9R7I92ORO": 2667, "A7O4GY472L6VY": 2668, "A1ODE5OC69SBIF": 2669, "A2GSJUETASGMO0": 2670, "A29ALY2WQXHMQZ": 2671, "A328TCK9WL7K3Q": 2672, "A3639XN4I9ED2": 2673, "AIOHU94GJFRU0": 2674, "AWIXDOCA5UDHM": 2675, "A2EU4FVLOVMVKN": 2676, "A1NOV41485TE0D": 2677, "A1BTG38XSGYLW3": 2678, "A3S0Y5GVW1CYRW": 2679, "ASJ0MKRFZC47B": 2680, "A1VCPMT1RRS7K0": 2681, "A3KUS4VYAOYWHY": 2682, "A27BONCJ1HZDIL": 2683, "A2L1U6TMQJP5SC": 2684, "A1EHDVLCSOU57Q": 2685, "A28YBL28P03P8V": 2686, "A3KGLXW3EYDTUH": 2687, "A601IGAG8FWGW": 2688, "A234X1MVIMPMMC": 2689, "A2FRAS05LEI6JJ": 2690, "A11XLS2X7AO7PQ": 2691, "A2QPY6J33YV1ZZ": 2692, "A28508SUMB7EQG": 2693, "A16V9XOFCL1TJ5": 2694, "A1KEPD71NTGA5H": 2695, "A2D2XKSXEG3O7F": 2696, "A1C1P6F3UQC97G": 2697, "A2MHK2WJZ7HJ5N": 2698, "A30KRD5W5FS21Q": 2699, "A11J81ZI9KAERU": 2700, "A29UK7GM2HXMIE": 2701, "A10H63KUGJEPAJ": 2702, "A29JV56YIQ9MVT": 2703, "ALO81PUAXWMVX": 2704, "A3RGN75LHYAG8U": 2705, "AQM73IWC4LFXS": 2706, "A3VTOLNB5N6FVP": 2707, "A5GPH59NDWJRB": 2708, "AYO1146CBIV5C": 2709, "A3TIJLY4VX8CH3": 2710, "A24ZMNWTW8AQUR": 2711, "A1N46G8TKM3ZQB": 2712, "A2G7B7FKP2O2PU": 2713, "A3C1QYGEET3BVY": 2714, "A34VN05UN1OBJ3": 2715, "AK9N5IQR1P192": 2716, "A34BJE7YQHRZNA": 2717, "A21B9M2H244JYM": 2718, "A3ARKGHF6LHFV": 2719, "ALE3ORJUOOAHV": 2720, "AIEEK7AHXKZCC": 2721, "A3HWV2YLDQ3XQ2": 2722, "A2BYZFC6T5MINP": 2723, "A18ECVX2RJ7HUE": 2724, "AEQRB6E891PTY": 2725, "A1F85UIFABI2MH": 2726, "A210B00WZ0YTQ3": 2727, "A1190GQQ1BTICP": 2728, "ABY77ZEHN9WLU": 2729, "A2IQV2ITUT56A5": 2730, "A3MDA891A1EPT8": 2731, "A1UQBFCERIP7VJ": 2732, "AHQS3N2QQZ9N6": 2733, "A28FJ93TJSSQS4": 2734, "A2ILR47L0NFWH1": 2735, "A24BBK1NFZPPJS": 2736, "A2YI5YCSUUR6OO": 2737, "AU5GGM8NG0H00": 2738, "AZZGGWZV5VR74": 2739, "A2SMI76ENKI0CM": 2740, "AMQ80PCZVF0Y3": 2741, "A2HUY8NQ445K7F": 2742, "A7YZHBFH7CERB": 2743, "A3U8KLEHUQK3J9": 2744, "A1K3N7T7Z9VURF": 2745, "A23WEMR6HY38W2": 2746, "A6U4W0DXLYKVU": 2747, "AO6BNTQV9GNC2": 2748, "A3K7RVCWO9MZQL": 2749, "AHTC9I3LBMAUV": 2750, "A20RZM43LBZJL1": 2751, "AG7XUJZ0D5EJ5": 2752, "A1DAR6U4E4LG39": 2753, "A2NO78FL32PID0": 2754, "A3B81D6NAXWJIS": 2755, "A30638B9S2GOM8": 2756, "A4SYP9YL5FKS5": 2757, "AFQ7VK2GL265J": 2758, "AIT674N3HE3RC": 2759, "A30W8I4SD1H21K": 2760, "AJENDQXZLWJSQ": 2761, "A2AVE8Q0EXDFAE": 2762, "A1EZGIAIEJ8Z68": 2763, "A243046YYZXJBI": 2764, "A3LL8PH49PZUG7": 2765, "A9FVHYY48O1UP": 2766, "A307132HLIZNSB": 2767, "A2XPKW9APTROUT": 2768, "A2M902FIGG3CDI": 2769, "A3ML8K8HH838BE": 2770, "A2USB35NGKBSQO": 2771, "A1ILMYA3Q75ZBI": 2772, "A12YPN6IFWKN93": 2773, "A35404F49F442O": 2774, "A35Y8XKVYHJGIS": 2775, "A347OT8UFA8I16": 2776, "A2KLG26QWNDIPP": 2777, "AGDDJBAN2MCGN": 2778, "A1N1ZSVWOX7WUB": 2779, "A184XTCFOCLX7Y": 2780, "A2GWWLZTRRE5HO": 2781, "A3NZSS80F98FOZ": 2782, "A30YWSM4MPDZ6A": 2783, "A3T4217DZDJV8W": 2784, "AU6EAMZ5MVS9": 2785, "A16WPA6JV83YXT": 2786, "A2ZFS1ETNMDUX1": 2787, "ATJV9TWMRNF8K": 2788, "A3RF46CL8GDIN8": 2789, "A3BVDW4DOLJAN0": 2790, "A1J5PASA4OMBI4": 2791, "A3BFG2CWAS73BL": 2792, "AGS62R4KZN46K": 2793, "A3J336068TGGHV": 2794, "A2S0SHEWROXG8": 2795, "A1JYB33LX3RKW6": 2796, "A334350WHD7BAT": 2797, "A27O69EB4Q36UV": 2798, "A2S73Z7ZR6HAMX": 2799, "A2M0ZAK33EIEME": 2800, "A3LQCSMM1V6M0R": 2801, "AS7SB0A3QKVQV": 2802, "A1I4NHYX40MFD": 2803, "A2BZ7MYTSNYMEW": 2804, "A1DO6DKWF3CMBD": 2805, "A1LINA8MCSONQL": 2806, "AYNRALJ4X1COS": 2807, "A4S284HLU7R9O": 2808, "A1PPSHNV1KJ5X3": 2809, "A1IIT6KQNH7QX1": 2810, "AR7AZKSV19BE0": 2811, "A3M9ONYTPETC63": 2812, "A2ZBA3VTSGESA2": 2813, "A243J19UMWOXRS": 2814, "ATXXM6XE0C5WJ": 2815, "A2OS3TIVAKUAHG": 2816, "A3M3W5GV0HIQK4": 2817, "A3OYI3FF0J9L9I": 2818, "A2HRQLIS0CS2OH": 2819, "A1SSIDDDCCK1E": 2820, "A2EI4VOT1F8V62": 2821, "A1UV263N7BF8XG": 2822, "A5A8A89CHG3S8": 2823, "A67ZXSOC2XH4O": 2824, "AEG3I82BVE2ZK": 2825, "A2KP45DO3RY4RG": 2826, "A3EFSLEMHNPP6A": 2827, "A2ZY3S7SD3QO8Z": 2828, "A3S8WLKSVWTZJV": 2829, "A2RHDFFD4EBJD": 2830, "A2CLF0H9PUZ96X": 2831, "A15DKVM598GQKS": 2832, "AGXND93DHIL81": 2833, "AYCDZQ43FGKR": 2834, "AHUG3OLOJ9YJO": 2835, "ABP6MAR8P6RLU": 2836, "AL4UTCPCSKNU1": 2837, "A1VDMXHHH5DI7P": 2838, "ADJAF7ZFZ25EG": 2839, "A1TS27MVS1WGWI": 2840, "A3PFT7FOTOKJ2P": 2841, "A3RJGP3MFFG6PV": 2842, "A1POL23KPA064A": 2843, "A3KHS90UO8FHWP": 2844, "A255JQANDJW0VN": 2845, "ARHKXVW7WYOOR": 2846, "A3IVCUIGUZQJ9L": 2847, "A11CV6M1H8S1EC": 2848, "ASHCSWSX2K6SQ": 2849, "A1V79H5LKYWMP1": 2850, "A1GYOSEAJ5EEK1": 2851, "AS7289468B8IR": 2852, "AA55VDAG0XXRA": 2853, "AGICS3306D8QD": 2854, "A43R2SARLQZ5B": 2855, "A19PKOH7OWJY42": 2856, "A2HZ15YBAJVW3R": 2857, "A2WYTRZHKIDZ0K": 2858, "A1I1DI692HQ0F9": 2859, "A25FJ8W6WCBFEC": 2860, "A2OG0EAIC2PNSE": 2861, "A20P7ZVZ36F4IU": 2862, "A2Q5DZRXBR6KAT": 2863, "A39GL1J7TN9LDJ": 2864, "A3L6TYX6YDQ13C": 2865, "A2OF39RWPPJNTR": 2866, "AGUBXH4PCEPY": 2867, "AXSMYWPZY4JAW": 2868, "AEE8969U5MGU3": 2869, "A14IW8KL9JGS2H": 2870, "A3EVVLVNG4QLI0": 2871, "A2NO09KBON4QOD": 2872, "A2WAJZWA0IJSQP": 2873, "A777MMP4S7S8O": 2874, "A3OUMZ8OZBMKRP": 2875, "A1UI8YT4BVQB0": 2876, "A3BV0WAXB8IULS": 2877, "A35QGS8D3I65NL": 2878, "A11JWVCT7N93NH": 2879, "A18SQ4EB8J8H13": 2880, "A1F02K9DX6HVHR": 2881, "A1OU6YUT7B0FV0": 2882, "A2PANJK25TC3CU": 2883, "A3HS4R46MZ87RV": 2884, "AN2AI0NUCJZIB": 2885, "A1EIAFI297P6YU": 2886, "A1S1SSE7HQDZEW": 2887, "A1JWUGHXT5HP39": 2888, "AY1LZ41VDDSPL": 2889, "AJRNC98E2ADGL": 2890, "A1YLRQL1XZBKCS": 2891, "AVHMOENRENU3L": 2892, "A1S7TXHM2VM5EF": 2893, "A3DN1EHYLP0IIA": 2894, "A20W9PSUAKDRN1": 2895, "A2318YEO923PC0": 2896, "A2BCCIUEWF210O": 2897, "A3JBJWPDD07B40": 2898, "A13E51ZEL1ZU7M": 2899, "A1QVSH3CRJHGHJ": 2900, "A20FBQSSFW1WPX": 2901, "ABIXH2YR8A86G": 2902, "A1UNM2BK0XPZLS": 2903, "A1EDG5ATUW3AYS": 2904, "A1FJNZ6GKM516K": 2905, "A23EQ805N1FAXW": 2906, "AWYMS1BNSG38Q": 2907, "A36S07OGN5FIO8": 2908, "ARPE7MWT1C3SM": 2909, "AUYBAV9NS20P5": 2910, "A1QKFWY3GTBDRY": 2911, "A2WKUC4FX8PPXA": 2912, "A102300ZYSDHRR": 2913, "A2TOD5KQVOSJCB": 2914, "A3TRRM13LNZ572": 2915, "AOEPR1OBL8CMT": 2916, "AC10U1A9F1X88": 2917, "A1P3B2YVXR6ZSZ": 2918, "A1DW6V7M2E335Z": 2919, "A3385Y17LXNGF5": 2920, "A2RKTFRM6YRK1D": 2921, "A23KSLZZ6CQJ7O": 2922, "A2LZFG6JQDHBJ7": 2923, "A3AUHT475KOF2S": 2924, "A27QHUP69EN6FL": 2925, "A1L4MFMJHRUE6A": 2926, "A38PZE4HZMI0QV": 2927, "A3M6XJ55L517LT": 2928, "AKHG70FKKHDTH": 2929, "A2UM0WJOL18IOX": 2930, "A2OVBO8Z3GALOD": 2931, "ATL4PY7I3HAA1": 2932, "A2UV26OF9LZ4ES": 2933, "A1LS4HTJAXVI8B": 2934, "AF1B1M9NWBVH2": 2935, "A1AKQ1YUS4BT82": 2936, "A2HMF8ZR67BNZS": 2937, "A1HM4GGGNKZ37B": 2938, "A2068BC3ZXAVJQ": 2939, "A21U4DR8M6I9QN": 2940, "ATI5QY38IY3NV": 2941, "A2RMQWK75EEN7R": 2942, "A1ACM1CBGORBN1": 2943, "A3JT29L4YFEIMJ": 2944, "A2SDKX7SSZ2P99": 2945, "A3BG6DCAJCL61R": 2946, "A1B1J07QUM0OLN": 2947, "A1NHZQK05X8ULH": 2948, "A31E2473ECO084": 2949, "A2VAYEHMZGXATX": 2950, "ADX9RRR1Z253S": 2951, "A2BV5EZKDX8OA2": 2952, "A13TAZK9Q95A35": 2953, "A15X5I17CU4I2H": 2954, "A17TASZJT6Y39D": 2955, "A2GHU8I0P3HFRW": 2956, "A2PSC7LUNIDEAH": 2957, "A2GY5WCU9PKTMI": 2958, "A2IKX7H2PLHULP": 2959, "A2ECM9HLMC242H": 2960, "AX0ZTNX6KVJ40": 2961, "AX148M3X6EUGN": 2962, "A2WTDSR5M9OGWI": 2963, "ANA64LWDCB25A": 2964, "A2K21IAPLTPF3Z": 2965, "ANIO0QXV2HJ1X": 2966, "A29CQ2U389HYOX": 2967, "A28RABVVESBLBL": 2968, "AKVJY23S6JFH2": 2969, "A1DKO10KSHP3PS": 2970, "A3RSPP6Y8SKVR1": 2971, "A1SZTF2J27RUF3": 2972, "A36FD1FT8RZ0B8": 2973, "A1DS6TA9S6KY70": 2974, "A2TRPBDNFSO1TL": 2975, "A29P65DEEZIEB0": 2976, "AGTZU3YUSRSOO": 2977, "A22PHKFFVGZ9X6": 2978, "A2NC8NBXI5NPU7": 2979, "A23IOT68MCMXMP": 2980, "A2BH950K3IQ0UQ": 2981, "AAA0TUKS5VBSA": 2982, "A2CS1R0PUQHVH0": 2983, "A2CPM6AEJHVNKL": 2984, "A3NM1MT3Q2FHXV": 2985, "A32EOHLFZYXJEP": 2986, "A1UMSB7LAW0RIR": 2987, "A31XW1RTQ4ZG9W": 2988, "ACN76NFHYL6JK": 2989, "A3BHZ8P7G3NCW9": 2990, "A2ZIPVL3ENCP08": 2991, "A1Z008CD2RW2W5": 2992, "A3RSGP8FYW1T2Y": 2993, "A2ZGPAIV64KOYU": 2994, "A3U5HKDHPYBAK3": 2995, "A1P4F6HIXU6WYE": 2996, "A1H5936RLPJ3B8": 2997, "A2ZOLVZH1BCX56": 2998, "A2RHJA5OXJM0O0": 2999, "A12ZFSESFYJF2G": 3000, "A2WN3EE62XMPTC": 3001, "AUUN34NT677XH": 3002, "A2XO1VNKN5GAGK": 3003, "A3O89SVYI4KCUI": 3004, "A337APYDFHB9V8": 3005, "A1E0L2V60U8H0G": 3006, "A0916357J9P21ZUYUZO6": 3007, "A2O8SEFGLPBH2O": 3008, "A1G7GN2T2SUEQD": 3009, "AF2HX24P7K1FF": 3010, "A21I717LTVC1Y": 3011, "A2HOLM5I1ARX9J": 3012, "A1NX66HPC962K4": 3013, "AYYWNJS1S12FH": 3014, "AO6MLL9BTVD3D": 3015, "A2P94P50FZL87F": 3016, "A37X260ISIDBM5": 3017, "A31VIMZP1Y6IUG": 3018, "AI4YSOGQGYCLH": 3019, "A3M9YXQ8U6ZKB8": 3020, "A36U7QMYILRLSW": 3021, "A1YGDHN09USR72": 3022, "A2PKIQN4VJCPQZ": 3023, "A332L1DH4A3OK8": 3024, "A33X4R7LU3OFQ8": 3025, "A3FLDCPC36ELU": 3026, "A2XABWPFYZREVA": 3027, "AS5IDC9XGSXSZ": 3028, "AYK7WWZKMVQQV": 3029, "A1RUPZ1HXPLBII": 3030, "A2PVIYFU9YH4NY": 3031, "A2P8XCV8PBKJQE": 3032, "A3A27DCLE98M3M": 3033, "AO0K0L635GCIG": 3034, "A1NLBKKUFURP48": 3035, "AXRIWVPE39ST1": 3036, "A3OUWCE8CHWCHJ": 3037, "A3MLE6CYAGK3R3": 3038, "A2V64H8AOAD4TJ": 3039, "A2YT6UH8DKGZ1Z": 3040, "A3D2188UIM5AKE": 3041, "AGO3PAULF9KUE": 3042, "A2KMJ4O4ZAH8GI": 3043, "A37QX2520O8Z4X": 3044, "A2QXL3YMPOMR24": 3045, "A1RXWDHS6V0E5L": 3046, "AE2P8VSPXQ7LG": 3047, "A1VTERS1W47RIK": 3048, "A1YOGC8UF2RCHC": 3049, "A1WUAZSEDLWNZN": 3050, "A1TNUZDZJTKMGW": 3051, "AW77KBRLVDD0T": 3052, "A1XIRB17MOLXPB": 3053, "A2GLLGEKQOWIT5": 3054, "A3HX7GD30O1MID": 3055, "A1S5LQ4W3T8401": 3056, "A1TSK3TFSE0T5N": 3057, "A2S732BSAE39CR": 3058, "A3P8N3YORM08CA": 3059, "A3KYPMICTZ3GZX": 3060, "AB4R0LUIG837W": 3061, "ALSB8M49AZ99R": 3062, "A1L7ULDIYG98VJ": 3063, "A322VANY4JAOQB": 3064, "A11X1WHC7P6DGN": 3065, "A13RTN901YNT7S": 3066, "A2CJNSXZYMA4Y8": 3067, "A1LLVL4YI9Q30C": 3068, "A73L4QLGV7ZV0": 3069, "AQDJIMQUK006D": 3070, "A25DU5SGL4D49Q": 3071, "A1DQWNPN03IEXN": 3072, "A3ER7785BOKGER": 3073, "A2J6PW8IUP505I": 3074, "A3A6H97D6OOKT7": 3075, "A2IQ2DVZK4YZCW": 3076, "A38LEIUPC2EJD6": 3077, "AN0WCLS9TNPPA": 3078, "A3LYGOZAMC2KZA": 3079, "A1OQQSBFCD2T4O": 3080, "ANLZVUO97Q1V7": 3081, "A59Y0ZV1VX46K": 3082, "A1RXXM0U0QGGJU": 3083, "A16GWMW2GI8XUJ": 3084, "A1SYEY0VXLA17Z": 3085, "A17D2CT8TAPMSG": 3086, "A1LJT1UMMNEMGF": 3087, "A35G12ZECNXLXL": 3088, "A2LA1KY47VJPZ9": 3089, "A3OPCXOIW7ZTGG": 3090, "A2LQ2ZNPGXZTVR": 3091, "AQEJXZW1O9O7O": 3092, "A1HWF0VV8AWJTQ": 3093, "A1XSSG2IQL1023": 3094, "A2YO1FC1A7YRSW": 3095, "A2JXJWJZPLH2FR": 3096, "A1P1O16N3ROSUY": 3097, "A2Z1JNMWCZX88V": 3098, "A23R0SL5M3HLPU": 3099, "AFX791XGHHMDU": 3100, "A2QYPEC9H2H6W6": 3101, "A3CLXS0OFIYIVW": 3102, "A1KT19TDP9VE63": 3103, "A1AXBN25KBBWSC": 3104, "AIBZYH7KI1AF6": 3105, "A2EJLYWOA9Y08O": 3106, "A3PVCWI9OXBBLW": 3107, "A2GW2ZOWS2IX3Y": 3108, "A2VEP9IKAW8YBE": 3109, "A3W29QTODGMKYC": 3110, "A3SSBBEGNC7G07": 3111, "ADDDFVHP3CSVA": 3112, "A2GP6XJ1V3MM3L": 3113, "A306NASGVUDFKF": 3114, "A1CM8LEX46O21E": 3115, "AR0ENM97GNFS8": 3116, "A35YFLKHVNI37": 3117, "A32I1W2R5ZI8H3": 3118, "A1L1S42BOGPF96": 3119, "A3K2FR9AJEF8XZ": 3120, "A3IMBPNQYEZUWC": 3121, "A1NRRU43MYI9S0": 3122, "A3G8XY7PMN4RBA": 3123, "A3Q1J68QY1MZQ9": 3124, "A3HG0DNFURFXR4": 3125, "AYUF7YETYOLNX": 3126, "A167ABU99FT4OC": 3127, "A37R3P5JFNQG8S": 3128, "A1Z6LEOOIN1ISV": 3129, "AQDLZ51L4XC80": 3130, "AHRAGCS2CUIA7": 3131, "A2ICV9NWBF514G": 3132, "A1BT6759WL0OVI": 3133, "A1CP6NZKDQG4FN": 3134, "AGWMLV54XZ1K3": 3135, "A45S6D1P309G9": 3136, "A1UINGIK3UG77D": 3137, "A3GUK4RWXKHS9I": 3138, "A20GTJ1G6FAGN0": 3139, "A3ATKIU6MZZ4MU": 3140, "A25B8W9VSY0C5Y": 3141, "A3KT85K6QPMGSV": 3142, "A9KLAL1CXZ0W5": 3143, "A2JVBJUU2DL0WA": 3144, "AIK0G28AWIL17": 3145, "A381MT950I6KRL": 3146, "AY91MQZZR750W": 3147, "AGJRUK27RBVYS": 3148, "A2V2URLB31HG59": 3149, "AZ0PCEZUTF5QO": 3150, "A2RX62V4E2BF5Z": 3151, "A1ZCSSCAGBCD49": 3152, "A33HIV8RXRDM88": 3153, "A13QN9DLFWOHRN": 3154, "A357B3PUHSVQA": 3155, "AKPG8VQBS0MWR": 3156, "A3F480SL44YP1J": 3157, "AQ2QMPLNWM706": 3158, "A1QPLOGZM1F7E8": 3159, "A60D5HQFOTSOM": 3160, "A25EOTX5I354I2": 3161, "AHZVX40D3P6CH": 3162, "A2LVLT1HHB55T7": 3163, "AEJLSH9DCJ3VR": 3164, "AMLTWG4BNQ17T": 3165, "A3MEMX0XF00TBD": 3166, "A39LRLKACX89IP": 3167, "A1JXRXYVSUAW6I": 3168, "A3E9WG5BEAFF3T": 3169, "A25IYL8L9LZNH3": 3170, "AT9U5ZE5OO84C": 3171, "AVFJ327UXPXLF": 3172, "A1G4J9LJ9TQZWI": 3173, "A18VCM7Y7HK6EW": 3174, "A11Z3ANM4PQFMH": 3175, "A2V1MAUHH1YHKK": 3176, "AJC7TSNP5UAWN": 3177, "A3NQA378KXTZQM": 3178, "A2NT1LGR2BYP0I": 3179, "A1AD4XP47VS56Y": 3180, "A1K1ZKOHP4RQTW": 3181, "A2H6LHCM3AR3YV": 3182, "ASG42G9QTBUX1": 3183, "A3NMQEQPT5LDIA": 3184, "A1TFMR7RE985MF": 3185, "A2XNOB1T796Y6B": 3186, "A1CCMW354ELJ3U": 3187, "A2XUSCBG6JC86W": 3188, "A17PDSMPB7HLYZ": 3189, "A20ECIBBYIEXZ2": 3190, "A1O4PNHACFEDEM": 3191, "ARASMD17H0WEZ": 3192, "A2W9I628I6SE1U": 3193, "A2TCALF1IX7S42": 3194, "A2RVCF21L2NPU5": 3195, "A2CUWCJHUPGL9W": 3196, "A1UQUDT2Q0YENM": 3197, "AP9Z703TP9YCM": 3198, "A1CC3G24842BG6": 3199, "A1I2U8NT5J6P1N": 3200, "A2PJYNJ7NPE4BA": 3201, "A16NRV54CGOO69": 3202, "AWJBO5XGIW8ZS": 3203, "A2F1P10GGZ7K2T": 3204, "A181TIQPGSTYH6": 3205, "ACN5JM2KDK72H": 3206, "ADS99W8WMEXZ2": 3207, "A1RLP0R1N8H8C4": 3208, "A1GMGLN1UKXAD1": 3209, "A1575JUI75IY6T": 3210, "A3KVT6K69N14W4": 3211, "A3SMR4HRFJARSC": 3212, "AZ9N3928BGQ0E": 3213, "A1VGXHHR08G044": 3214, "AI133BDJHFORJ": 3215, "A2NWWLC6C51S6E": 3216, "A3G0F3VRM187KT": 3217, "AJIOCLNVCPYRR": 3218, "A23VNS0WLAYNT9": 3219, "A1806K4AD7LM0W": 3220, "A1C8J8N4BKDFN3": 3221, "A208UDKWBYILO8": 3222, "A323WZTV4TW9T": 3223, "A3H7BO1T97SCAX": 3224, "AACR8PZRSFG3J": 3225, "A14V1KIQU0U4RV": 3226, "A1TWWTNPJN37M1": 3227, "AVLCKO0ZI8AG": 3228, "A2DXENZNO2JT4F": 3229, "AHFGCH8LANEZK": 3230, "A26SO3TOT2TLJE": 3231, "A3H0JG9QWD3JIN": 3232, "AKBYINIUXK5VO": 3233, "A4LMOYHT1RO2D": 3234, "A21V0NROAQL7A8": 3235, "AX9PVIIHKST28": 3236, "A325AWZXD3KC8C": 3237, "A2CA0CFUZS89OG": 3238, "A3OEQRX60SVGN4": 3239, "A1X7TX6H43L9K2": 3240, "A31EGFG5C4TETH": 3241, "A1IUNHVZ5C0F0Q": 3242, "A17JOFI9IDPSES": 3243, "A3VL263FW0O1JL": 3244, "AM98QA93XNIKJ": 3245, "A28EV72THMZRVO": 3246, "A39HDNPW97LD76": 3247, "A3UW4XQPG44U5M": 3248, "A3C5EZKG2J4M0L": 3249, "AI8SX6U5K8TN1": 3250, "AA9FGJX4HTGPG": 3251, "A7XUSKJ6H9DI5": 3252, "A18TGY5T94H55U": 3253, "AIRI6RQ4IFT22": 3254, "AG89GSACSJZOQ": 3255, "A3J2OO5TNPMN9M": 3256, "A13J2PGKNMJG1K": 3257, "A1H554HE81ODEX": 3258, "AIDSPQXBHLAH0": 3259, "ATQWHIT4GCWFU": 3260, "A1DZ8JQ4PRJ2A2": 3261, "A3RQLF4ZK9ISDE": 3262, "A3JRW716H3AX14": 3263, "A1KI3173CO6TK2": 3264, "A3VGSA71W3ZPM5": 3265, "A4EG8M5Q7C7WM": 3266, "A33WOI846MMYGI": 3267, "A3E0W5O1MPW3K": 3268, "A2PK8USJ6P7C3": 3269, "A14EPTYN50XSZV": 3270, "A3OZPCMM35U2EY": 3271, "A2EG52F067L2TT": 3272, "A3JTLZ958Z78RC": 3273, "AZMISC9FAUBIR": 3274, "A2LXC5ZHHP0WXP": 3275, "ABEAUXVVB2E1M": 3276, "A2WVF9ZQ068DN0": 3277, "A18HE80910BTZI": 3278, "AQCL9JWDUGUO3": 3279, "A3QKT9VTCI1PB6": 3280, "A33RT6A0C6OMIQ": 3281, "A38BE06WWL20AY": 3282, "ANRXH0BVEAR6B": 3283, "A2X2WTEVCZ5L8N": 3284, "A2NBCCFDISGUQT": 3285, "A10Y058K7B96C6": 3286, "A1FPQ54AIB26L0": 3287, "A1LHAXBM5GBJS2": 3288, "AMS2CPERWN7JV": 3289, "A2U6GHU2EMC5M5": 3290, "A4JI0CFOUAXBR": 3291, "A3SAIP0NEPUU7J": 3292, "A1QCULR3SQ9IIP": 3293, "A1HOLE9R6WPT85": 3294, "AO7OKX2B4O7CA": 3295, "AM2FXMJCQAHEE": 3296, "A1H4OY28I9ADYL": 3297, "A1UJBAL0ZT6O3D": 3298, "A6G24O29K0P6R": 3299, "A1GHKSWT15FDWU": 3300, "A33JGP7NR4BV8W": 3301, "AF1K4HX68DSJY": 3302, "A3AWV00ZU7MSK1": 3303, "A141W8WHW9AC3H": 3304, "A3GFK7F5IUF60X": 3305, "A1JBBR4MNGQ70G": 3306, "A33VI944SO2YCN": 3307, "A1JFYDF90M3WF5": 3308, "ADVSW4W1HHYF7": 3309, "A1ZGHA3IJV01BK": 3310, "A2MGFQP3MEU5IS": 3311, "A3NVB6HKMUH2NM": 3312, "ACQYIC13JXAOI": 3313, "A1ZNCMFIECPTVT": 3314, "A2BQWD54CXBX6R": 3315, "ABQEKKRD6WZFA": 3316, "A2EF1KIQ7TMPPF": 3317, "A3RBBLXX7BD6ZX": 3318, "A24IOBGALGOZCB": 3319, "A1I477ADGMLVJM": 3320, "A1NQK5MH9GTJ6S": 3321, "A2IYX5W3A1N3VB": 3322, "A3HAA7H8PBVM78": 3323, "A2FW71YE37Q2YO": 3324, "A67FO36PIXNUV": 3325, "A2OX8O4TS0X3X8": 3326, "AX8KKN5A1PG9E": 3327, "A75JW4F7P98TC": 3328, "A1DZIHLWJJRUW": 3329, "A3SQGHL6AQ2R9E": 3330, "A1QLYFY3O1RN8V": 3331, "AGZSVG7AE9CMV": 3332, "A2MSF5K7HM8TF1": 3333, "A1WOX7A4W048GK": 3334, "A1XE7YK8O300KM": 3335, "ADR9KROI61DFJ": 3336, "A12LXY31MFASAL": 3337, "A2DP8076RMUZT1": 3338, "A3RPD7744JX3VE": 3339, "A14ASZDYCXUTI0": 3340, "A3DN806HA6HHV1": 3341, "AB7V9FFK51EKT": 3342, "A2M6TPSY6D3IPP": 3343, "A3A3YG4XF7TQAC": 3344, "A2OA9XX2PCPDO": 3345, "A2E17WW862NR24": 3346, "AQO3WDKL8Q7BL": 3347, "AFTO18B2WM764": 3348, "AR8TLB6QXH1W1": 3349, "A343ZOGUM56IC2": 3350, "A1PPJBF43IJ1W6": 3351, "AWJUV8N4YKSL7": 3352, "A1SYWFYDBXHRHF": 3353, "A3IF06RTB34SWJ": 3354, "A1T9YI02JUBIPZ": 3355, "A1YOLYHGL6G9XB": 3356, "A67O76LTCO01K": 3357, "A3FSZAGMC2WSRO": 3358, "A1BLOBFHQ17QFD": 3359, "A2VWTQPIU63DD4": 3360, "A3N4QJP6D70NVP": 3361, "AT7RSYNRMDA6Q": 3362, "A1EB6OCXNZKRI8": 3363, "A1TRECFDGFD4LE": 3364, "A5BUH1D121NQC": 3365, "AKOCTXJ5KV8T2": 3366, "A3VHRN8GV419D9": 3367, "A2RIHQ4AFXI30F": 3368, "A3OO9PPIOXIYJZ": 3369, "A377XOIB9FP6ZV": 3370, "ADS4TFYY8TJHO": 3371, "A14CCDURTA6ZMO": 3372, "A2Y33L0JWOMR4E": 3373, "A331MWI0W4WSEY": 3374, "A3SN8H1V126IIY": 3375, "ATZDGPMWR6N5D": 3376, "A25B1VQ8UIH82U": 3377, "AEOSWWUZ6DO1G": 3378, "ALC20AYEKK4ZP": 3379, "A3FKGKUCI3DG9U": 3380, "A3S1JUU9FXC8MQ": 3381, "A7J8Y1TDIN69G": 3382, "A1PK2OL2W8IWLZ": 3383, "A11UNM6QZ3XTZH": 3384, "A2ZY48F7RX4SRL": 3385, "A2L9OPJAAEK08Q": 3386, "A22RGEI19Z9AEV": 3387, "A2H2FT8WV5X6SV": 3388, "A39E7IWNHY62JT": 3389, "AAWUC8S00IXJF": 3390, "A2OHNA7PBBQ4C5": 3391, "A1VABWDOUQLULZ": 3392, "AQ40ACD5AC0DD": 3393, "A1DD5LYFQ3ZAOK": 3394, "A3EWUMHYMPD7IB": 3395, "A3U0S17XYK8XMJ": 3396, "A2BAAKZHSUGCDP": 3397, "A2G8D1VN3MVB6F": 3398, "A2VR6BK6U3080V": 3399, "A1FU5CN8V620TH": 3400, "A3E4EGAJSSL04J": 3401, "A3J4FUEUXPI5A8": 3402, "A3CXJIYYG6JWKE": 3403, "APPJNVNF4BFLB": 3404, "A1ZKZQPKU77Y62": 3405, "A110KACX3W12L9": 3406, "AGCZFGHW6FFGF": 3407, "ACT7UWXQSZ3EV": 3408, "A1A8KY344FDXZB": 3409, "A109L3WXD1SJFU": 3410, "A3RZOPQ42Q50B1": 3411, "A3EPJSPH03AS29": 3412, "AGFGY4EJ37VS2": 3413, "A3N27L13CWJ9HY": 3414, "A3IHI911PXMOW5": 3415, "A3TSEW1ANGIOZN": 3416, "A3TNM3C9ENUCFW": 3417, "A1WKEAS58297E5": 3418, "AJEDVT3OSUZCF": 3419, "A3V1AHX8P4R839": 3420, "A1RZ0J2CZZJOTX": 3421, "A3KNJ386MRBPZC": 3422, "A23LRGXH0BTGFZ": 3423, "AESNOYBYV9WGP": 3424, "A2XFOE9KPMXELR": 3425, "A2AE75HDESZFN4": 3426, "AGC1Z5C1NQ64A": 3427, "AKP89K0R96VWB": 3428, "A17FWYSN5GNFDH": 3429, "A1ZRD3WNHP8O3T": 3430, "A36HIK7UBPI0TR": 3431, "A3SOC0726SH4ZH": 3432, "A2UNV0XASV55UM": 3433, "A1Q222GZ16KA3Q": 3434, "A2XE0HMG75BCLY": 3435, "A259X6HZ51Q46N": 3436, "AXO2QG19806ER": 3437, "AN7QOIMW6QMQJ": 3438, "A32UN5NNLS24PV": 3439, "A1G7XVI1NU80YH": 3440, "A15H4Q3U7XXO8S": 3441, "A3V1IZ8C17LFWU": 3442, "A36623NAOKB62V": 3443, "A2J6OFQ15WBG99": 3444, "A3H2G9P613G0FG": 3445, "A1SGVSYOB70FY": 3446, "A2Y1QK5VT2QX3X": 3447, "A5AWAP14JF27L": 3448, "AE5GP2T742SA8": 3449, "A21WBIKZHAHFJE": 3450, "A1COW3DSUHUUE4": 3451, "AL69UV8T072NH": 3452, "AEIF0CWR6PV0H": 3453, "A25SLTMFZ9FT7U": 3454, "AUMS86MZELMS6": 3455, "A2BILUPJR1QK94": 3456, "A1OWKBICDH4CH8": 3457, "ALEM7BBUFGVYP": 3458, "A2JYR10B40EI3Z": 3459, "A2PU7XW1J998ND": 3460, "ANO5RR1KPU9FZ": 3461, "AV4V89ECN3HKH": 3462, "A2PQMHHCI4TJVK": 3463, "A1WSKBA4W4Z74H": 3464, "A13EPWUSIYR4E1": 3465, "AO5EKE61NBOGI": 3466, "A3GE1HSX7QGME1": 3467, "ANLN2A1O4NIMS": 3468, "AJVY04L3BL4VS": 3469, "AKX7YE26PAMVP": 3470, "A16FKKOV6MYJHO": 3471, "A2S2NREEIHSK03": 3472, "A1PJW1DYGFZV99": 3473, "A2WYYGLALJBVIU": 3474, "A2P13ZMSWF3IIC": 3475, "AC0EB85YZY51Q": 3476, "A2C87W3P7PGG2Y": 3477, "ASZQ0FTRJEHUV": 3478, "AFVBZ7UDEDRUC": 3479, "A2ZEM44ZOG1X40": 3480, "A13D08OA1VG6J3": 3481, "AB42KD37ZMFWN": 3482, "A12QB51VZ8CGOT": 3483, "A2R6JRYUHY8P42": 3484, "A1LHR7EQE5Q2UI": 3485, "A3LDZ2GFPBMOY8": 3486, "A1YAHF2E2MWR4P": 3487, "A209PKR6FIJRI4": 3488, "A23V3WTYJUJIY8": 3489, "A1A371Z10JABPI": 3490, "A6X089IWIRR81": 3491, "A29LA15KO056BT": 3492, "A3M41B4AYJWFLT": 3493, "A2JGD65DRNR75N": 3494, "A2U0QQOF4O44LN": 3495, "A2LS6OJAHQYLPE": 3496, "A1EHVKN2E28S0U": 3497, "ARXHSWN3RMN93": 3498, "A2I97K9I4K6SSV": 3499, "A1QFXD00PN6VJ0": 3500, "A2R344HWN5N5F1": 3501, "AMYRCTEW5AR4C": 3502, "A3BBLQEB3IGRVP": 3503, "A23WBMYCXZCXAG": 3504, "A3BVF9HSE5F8ZC": 3505, "A2S9BVIIP3XDVS": 3506, "A1M5HJLJ6EDHFU": 3507, "A1DNFO9BEJJEYJ": 3508, "A7H3BAK83N2TA": 3509, "A2Y86NGI9SXBHM": 3510, "A1RDTA8WY3X614": 3511, "A1QXE9QBD9ERB6": 3512, "A2W113A4NBI912": 3513, "A3BR4X13C562NP": 3514, "AEYLQ33Y99OVW": 3515, "AV5N1KQK93VQL": 3516, "A1N0H5PETP7E42": 3517, "A37ILPDSY9ESL5": 3518, "A1DZ0O2ZXOYEGU": 3519, "A3IJY3PCGFJQQA": 3520, "A3E0MPZNN1NFNW": 3521, "A21UK8IM9C2S29": 3522, "ABDBNJ09BMIGK": 3523, "A2Y1NEVW8N54DZ": 3524, "A1FG0V3KRXAVT7": 3525, "A3VTWM27O0SZ42": 3526, "A1YLOROSPAULRJ": 3527, "A5IHDUC76S78S": 3528, "A3OIABTOKNJ4JW": 3529, "A3UCSS05QGW35W": 3530, "A3RVYGFA3T5VW9": 3531, "A3UWNRCTZVZKAQ": 3532, "A24FYJF4JCQE2Y": 3533, "A2XX02TJ94EH5L": 3534, "A2VJ3ZPUT58PJD": 3535, "A1D3KAQ1VY8LUG": 3536, "A2X49H6378IL4P": 3537, "A3JPRLR9A0VFFE": 3538, "A21PC5S0MIM6IX": 3539, "A2BKLHVB230M1X": 3540, "AYPJT8WPGJHAC": 3541, "AUVT779XSA1F8": 3542, "A2EHH30602WQTX": 3543, "A1OPJ07CRU2GX0": 3544, "A2ZOHKL28AM5GY": 3545, "A27OOJSY1RH1O6": 3546, "ACZ1YLFIKDG9U": 3547, "A2Q627PLWBDEYM": 3548, "AU9MV75IZYVB2": 3549, "A1WD3VA1TH59NY": 3550, "A68L07FQH4IQ6": 3551, "AT7YWFYN4BUWB": 3552, "A3742CA0ARJOMG": 3553, "A17WMMYCTCYDFQ": 3554, "A2BUAZW75V85QO": 3555, "A2U997LC7QHRSC": 3556, "A2PS5JKTTE6TSY": 3557, "A12066XBJS20IF": 3558, "A3I92O1R3S4H1U": 3559, "A2548ELQMB9QEN": 3560, "A1BNYFMPSP3AOG": 3561, "A2XHLAXMIQW7LY": 3562, "A2N85HQS62ZIS1": 3563, "A117NOT6QPCRMV": 3564, "AQ6ZF4PY7X3WX": 3565, "A38RSVBJSMZ83O": 3566, "A16M7YAIAOLPW": 3567, "AIWJCE18N71L4": 3568, "AKSMXE0CRLA5T": 3569, "A32GTFFK9J05VH": 3570, "A3BJZ3Y8UKIQ1G": 3571, "A308FNXU141T5F": 3572, "A3QOMXYGWJ6HYB": 3573, "AE78P0RCDNPZ": 3574, "A1DOS1TMRAS4MT": 3575, "A3K9LSAB4K21EV": 3576, "A1FFFEHK9K5XU0": 3577, "A1ZN9DE9VQXB6V": 3578, "A2001U1WVA2ZZF": 3579, "A2NJJ4JFF45TJV": 3580, "A38GYASIC1VQDI": 3581, "A2IKWRF4EVT3PG": 3582, "A1K1MDRX8D61LF": 3583, "A306GI4J03UI88": 3584, "ADO1ZPAH7DJ5R": 3585, "A3NH8OY5LUVOSZ": 3586, "A2H6KI5U0OPDCO": 3587, "AY1UCM5FG6VCG": 3588, "A8PPHFW7BW5UB": 3589, "A2GAR1ZPZFO28": 3590, "A12LN1UTGCPU4R": 3591, "A2DT9P6XQW3T39": 3592, "A2FYFGL9S37941": 3593, "A1Q69CMZ9QL9E3": 3594, "A34AGKU14DGF5K": 3595, "AT8HFJYB071N3": 3596, "A3SMY3BN9PMDK6": 3597, "A2CB5CJZKISZXI": 3598, "A31RQG6IXO0FN8": 3599, "A1OSZ0SN61MAEY": 3600, "A3TOFRVX4N9UT5": 3601, "A24YATZK2JF7IR": 3602, "AHZDZ7XLCB7H5": 3603, "A2AEDTLOUU2T8Y": 3604, "A23AG3Y9IGG0NU": 3605, "A18G130R7K8W07": 3606, "A2NSV9K5XUZ3BO": 3607, "A3QL857ALV5RCJ": 3608, "A1L28UXWSTSVSD": 3609, "A1C48NJP2ED5DN": 3610, "A1XURL0P01JA50": 3611, "A36HAT6OHPMNHN": 3612, "A1ZW2CNW69Z0VF": 3613, "A15I2N31VCSBH6": 3614, "A2Z5GY3909V6BC": 3615, "AVEOVIRYPMCSN": 3616, "AD1ZOPB0BBEHB": 3617, "A2SH6A32BE6NEV": 3618, "A38YS1DNHC3CVC": 3619, "AUU2G7AJ6E6HL": 3620, "A140ICK18NAAYR": 3621, "A1O6I7294KOSP1": 3622, "A14NA0W8ESGDSI": 3623, "A1QTHVA826XEOS": 3624, "AQNX0WN00JEVE": 3625, "A2SPV96SGOEO2": 3626, "A3DS0VAXL90E26": 3627, "A3SR9ULOZXWVXJ": 3628, "A2FLJCJ3SW0TUY": 3629, "A1YH6DMZOS59A2": 3630, "ATYUQROTHLNYV": 3631, "A2ESXEVEQB37I3": 3632, "A3NPVNPMXN8L2G": 3633, "A1INBQLNQNSHTK": 3634, "A3EBJDZ5N1UEI5": 3635, "A33NZ692P7BZ8Q": 3636, "A8VAO0Q5SML73": 3637, "A154UC6EHTSXAC": 3638, "A3OXM4NUGQKIQ0": 3639, "AR33KU52LIBF1": 3640, "A2ECTCPBTOGW4H": 3641, "A1E8XXAKINL0B1": 3642, "A3FA8Z7MQJ5JSD": 3643, "A2H7XVRD27L2QL": 3644, "A3AYSYSLHU26U9": 3645, "A2M1MNG7G40V85": 3646, "A1O229NVVDJUX2": 3647, "ALSAOZ1V546VT": 3648, "AJ3K3HKR9UFVN": 3649, "A3S5WYWYKSAI9C": 3650, "A3R4794K2RVU1S": 3651, "A27L5L6I7OSV5B": 3652, "A3HRDRQ5VAFPQS": 3653, "AA0BGTQHWKSQY": 3654, "AEASNN4Z1IWB2": 3655, "A3FMPT5IH0CJ50": 3656, "A20CR5MK7Q8M6Z": 3657, "A379IB3EYAEL5": 3658, "A221AYJCX6Y5WB": 3659, "A3JLOIXFM75QNV": 3660, "A3GK1O5S6188AJ": 3661, "AMCHLVS2PM9X6": 3662, "ATLH5AGWU672F": 3663, "A2H2I5FY1PUHP1": 3664, "AI5OS4RQQIUMJ": 3665, "A2LE2MFI4QTQY4": 3666, "A1P2XYD265YE21": 3667, "A1XR58IRKP3HEZ": 3668, "A240FRPD4MEXND": 3669, "A2AVMEB8PQOTTE": 3670, "A2F6NONFUDB6UK": 3671, "AKFTIYUSRKQVE": 3672, "A1Q08H4B9QGT2N": 3673, "AJID2XYGNFOOT": 3674, "A3H62VYLEK8X1V": 3675, "A1LAGS8H4A2DR7": 3676, "A2V98TS4QDDCG9": 3677, "AWCJ12KBO5VII": 3678, "A2PU5IDX61XJ7A": 3679, "AOWM3ZLHZF07H": 3680, "A3CNFV5UK26Q8A": 3681, "A3U6J0DLLDEWM2": 3682, "AQCJWSMSURQI2": 3683, "A3Z9QN0RCOHEY": 3684, "A7H1LWFBE905R": 3685, "A17WBBVKJH3F3C": 3686, "A2GK5S3ZF9Y8YO": 3687, "A3JCWGHCVC2ZNF": 3688, "A2K22IGDSNM0WY": 3689, "A3A9G2G3QB3NYM": 3690, "AF3BYMPWKWO8F": 3691, "A2K89R0B20LYHB": 3692, "AF74UAKV3Q3W0": 3693, "A21SESEJ8E52B7": 3694, "A1MXO11GL94AX9": 3695, "AHRNDSKWH1YBT": 3696, "AIJQU979J6UFY": 3697, "A1UKA7HUAQAMY": 3698, "A16QODENBJVUI1": 3699, "A2RQOO8VYAEZZG": 3700, "A3TPT3CINOTLDM": 3701, "A1V3PCKVCJ3TTZ": 3702, "A28TWWUAWFVCTR": 3703, "A13M9XSQ4O6NLY": 3704, "A1RR36YKJB917S": 3705, "A3J3OCM6PPWNRY": 3706, "A3MMMEQYQFE7II": 3707, "ACHTDPEQYSEQL": 3708, "AFTFND8CPQ34M": 3709, "A2DYW9Y2D8E43L": 3710, "A2RBC8IRQAZLWV": 3711, "AT53ZTTO707MB": 3712, "A1ZCYC0RHTRMZF": 3713, "A2Z8HBD9WFK2Z3": 3714, "A39E4C7YVVQ02F": 3715, "A2W0LMPC72GGTJ": 3716, "A23O8T3LNL9YY8": 3717, "A3GMRYV7VAYK5Q": 3718, "A33ROMADEKHQ4V": 3719, "A1HHPA73HHGABZ": 3720, "A16UMY0X6X7R03": 3721, "A3HFQT4IPBUA1P": 3722, "AXVKMYWNIHK7W": 3723, "A2J8DE8R94ZB02": 3724, "A3MLM6TUGHU4RZ": 3725, "A3RL0RFSSLJGKT": 3726, "AVL5IDEE8YA3D": 3727, "A31AVXMESQRQAC": 3728, "A5X1B2HBQUR3P": 3729, "A3L7RTXALWMO30": 3730, "A1POGCSD85PJCW": 3731, "A1TS45JWJVOSSW": 3732, "A38NHXL5257E3B": 3733, "AN81JUYW2SL24": 3734, "A3QCY8ODJBGFLH": 3735, "A1JOANG98KBFKU": 3736, "A3NPETMZXGIG65": 3737, "A30Z0GG96D11EO": 3738, "AJD41FBJD9010": 3739, "A2KS0FVY2CNJ8M": 3740, "A3QKYFU781YTKU": 3741, "A3K3SE4RK846WO": 3742, "A3TCMJ6GKZJFBQ": 3743, "A2CSJAVTPSLFS6": 3744, "A3FWGSJ3T3N5QW": 3745, "ABOVQ74OQRZCM": 3746, "AHXZ7JV7RMTGU": 3747, "A3GL5LGN7GZLR2": 3748, "A2M34TR2T9YAXV": 3749, "A1143YEAZYMYHJ": 3750, "A2MPXAJK3K61IY": 3751, "A1O2QIQK2OR5TC": 3752, "A5K3CK2PWYQ7O": 3753, "AY49JOXTLDOG2": 3754, "A3BZCJS4NORJQW": 3755, "A3RKYWYJH1HLMZ": 3756, "AJXZUXN05JWXV": 3757, "A3FHSLWEMH7JD8": 3758, "A2OAD5Y7MXUOFZ": 3759, "A3VZH0PWLQ9BB1": 3760, "A1OMXVXXP07F05": 3761, "A20XBV5UO5ZS2S": 3762, "A1H7Y5XKPGT0OS": 3763, "A2CNGARED6OWWU": 3764, "AE88D7OM7YU99": 3765, "A44OY8EFDM4IP": 3766, "A23OH5XOPXS6XI": 3767, "AF50DRVCXFMJL": 3768, "AOGM0FZJXFUHV": 3769, "A14L2638XC00EZ": 3770, "A79372WBA9IJM": 3771, "AY4PKA215Z3G7": 3772, "A38VL8YAHG1RPV": 3773, "A1C7Y31S5QXNTR": 3774, "A2MCC0XFURU2K2": 3775, "A2FNBD43DEZPM3": 3776, "A1KDM0N4UCEPHA": 3777, "A1H4OOUVRTZYNS": 3778, "A11440ZB6FEAKF": 3779, "A3MOZLFHIOG5YV": 3780, "A1FUBPW8U2RYUY": 3781, "A1D5RCOILPC9LX": 3782, "A3B6E2WUEKE9WK": 3783, "A2N786KHIFCKJ8": 3784, "AY3AVLL5IWW9": 3785, "A1PRZ3GE0C2ANS": 3786, "A1X6PXS7441VS5": 3787, "A32DYU82G6X3AO": 3788, "A11K70GWSB7A5Z": 3789, "ACR4HKUT808U1": 3790, "AE0337VVP8MRM": 3791, "A3U52V5ZAHZZKU": 3792, "A26A64X86VL1R4": 3793, "ADEZOPMPKK146": 3794, "A3TAF7M58DN46F": 3795, "A1DRM3JV6T5O6P": 3796, "A21B8AV7E3MPXE": 3797, "A1DW36J0ZTN8QY": 3798, "A2QRXQPHDMFCQV": 3799, "AP6L54VTCJKCQ": 3800, "A3G2MJPURQSCBD": 3801, "A3IMK08UX0I46A": 3802, "A1QSKSNWAGXKBZ": 3803, "A3B9RXJR7ENGPX": 3804, "A1XNZ7PCE45KK7": 3805, "A2KWE2ZM1EEBGJ": 3806, "A3RGHO0Q938FRS": 3807, "A3QGVH7WIATOSP": 3808, "A2D1258ES6QOQL": 3809, "A2UQC2G6BOM9E9": 3810, "A3LOAIRUUNO5IX": 3811, "A1CWXKAC4W0GIU": 3812, "A2EL2WXUKRU9BC": 3813, "AU4Y8JCQV2Q1U": 3814, "A13JH2NRRR2NF6": 3815, "A2L0GS3N2CXDWC": 3816, "ABBLKU5YUWVXH": 3817, "A36VWPU7SXWOFG": 3818}